Workbook

Sheet INSTRUCTIONS
A1: Workbook purpose | B1: workbook mapping sustainability report disclosures from 6 companies onto topical ESRS datapoints, quantify cross-company reporting overlap, and generate a shortlist for later scoring on ease of reporting and usefulness
A2: Important methodological note | B2: This workbook measures reported ESRS-aligned coverage in practice (from Sustainability Reports) - It does NOT prove formal legal ESRS compliance
A3: Suggested company set | B3: Bolton; Espersen; Mowi; Nomad Foods; Profand; Thai Union

Sheet ESRS_MASTER
A1: Source: ESRS_EFRAG_EXCELL | B1: https://viewpoint.pwc.com/dt/us/en/esrs/esrs/esrs/efrag-ig/efrag-ig3.html
A3: ESRS_ID | B3: ESRS_LAYER | C3: Topic | D3: Subtopic | E3: DR | F3: Paragraph | G3: Related_AR | H3: Official_Datapoint_Name | I3: Data_Type | J3: Conditional_or_Alternative_DP | K3: May_Voluntary | L3: Appendix_B_Linkage | M3: Phasing_LT_750 | N3: Phasing_All | O3: Quant_or_Qual | P3: Processing_Relevance_Default | Q3: Priority_Screen | R3: Keyword_1 | S3: Keyword_2 | T3: Keyword_3
A4: E1.GOV-3_01 | B4: =IF(ISNUMBER(SEARCH(".IRO",A4)),"Exclude", IF(ISNUMBER(SEARCH(".GOV",A4)),"Exclude", IF(ISNUMBER(SEARCH(".SBM",A4)),"Exclude", IF(ISNUMBER(SEARCH(".MDR",A4)),"Exclude", "Keep")))) -> Exclude | C4: E1 | E4: E1.GOV-3 | F4: 13 | H4: Disclosure of whether and how climate-related considerations are factored into remuneration of members of administrative, management and supervisory bodies | I4: narrative | O4: Qualitative | Q4: In scope
A5: E1.GOV-3_02 | B5: =IF(ISNUMBER(SEARCH(".IRO",A5)),"Exclude", IF(ISNUMBER(SEARCH(".GOV",A5)),"Exclude", IF(ISNUMBER(SEARCH(".SBM",A5)),"Exclude", IF(ISNUMBER(SEARCH(".MDR",A5)),"Exclude", "Keep")))) -> Exclude | C5: E1 | E5: E1.GOV-3 | F5: 13 | H5: Percentage of remuneration recognised that is linked to climate related considerations | I5: percent | O5: Quantitative | Q5: In scope
A6: E1.GOV-3_03 | B6: =IF(ISNUMBER(SEARCH(".IRO",A6)),"Exclude", IF(ISNUMBER(SEARCH(".GOV",A6)),"Exclude", IF(ISNUMBER(SEARCH(".SBM",A6)),"Exclude", IF(ISNUMBER(SEARCH(".MDR",A6)),"Exclude", "Keep")))) -> Exclude | C6: E1 | E6: E1.GOV-3 | F6: 13 | H6: Explanation of climate-related considerations that are factored into remuneration of members of administrative, management and supervisory bodies | I6: narrative | O6: Qualitative | Q6: In scope
A7: E1-1_01 | B7: =IF(ISNUMBER(SEARCH(".IRO",A7)),"Exclude", IF(ISNUMBER(SEARCH(".GOV",A7)),"Exclude", IF(ISNUMBER(SEARCH(".SBM",A7)),"Exclude", IF(ISNUMBER(SEARCH(".MDR",A7)),"Exclude", "Keep")))) -> Keep | C7: E1 | E7: E1-1 | F7: 14 | G7: AR 1 | H7: Disclosure of transition plan for climate change mitigation | I7: narrative | L7: CL | O7: Qualitative | Q7: In scope
A8: E1-1_02 | B8: =IF(ISNUMBER(SEARCH(".IRO",A8)),"Exclude", IF(ISNUMBER(SEARCH(".GOV",A8)),"Exclude", IF(ISNUMBER(SEARCH(".SBM",A8)),"Exclude", IF(ISNUMBER(SEARCH(".MDR",A8)),"Exclude", "Keep")))) -> Keep | C8: E1 | E8: E1-1 | F8: 16 a | G8: AR 2 | H8: Explanation of how targets are compatible with limiting of global warming to one and half degrees Celsius in line with Paris Agreement | I8: narrative | O8: Qualitative | Q8: In scope
A9: E1-1_03 | B9: =IF(ISNUMBER(SEARCH(".IRO",A9)),"Exclude", IF(ISNUMBER(SEARCH(".GOV",A9)),"Exclude", IF(ISNUMBER(SEARCH(".SBM",A9)),"Exclude", IF(ISNUMBER(SEARCH(".MDR",A9)),"Exclude", "Keep")))) -> Keep | C9: E1 | E9: E1-1 | F9: 16 b | H9: Disclosure of decarbonisation levers and key action | I9: narrative | O9: Qualitative | Q9: In scope
A10: E1-1_04 | B10: =IF(ISNUMBER(SEARCH(".IRO",A10)),"Exclude", IF(ISNUMBER(SEARCH(".GOV",A10)),"Exclude", IF(ISNUMBER(SEARCH(".SBM",A10)),"Exclude", IF(ISNUMBER(SEARCH(".MDR",A10)),"Exclude", "Keep")))) -> Keep | C10: E1 | E10: E1-1 | F10: 16 c | H10: Disclosure of significant operational expenditures (Opex) and (or) capital expenditures (Capex) required for implementation of action plan | I10: narrative | O10: Qualitative | Q10: In scope
A11: E1-1_05 | B11: =IF(ISNUMBER(SEARCH(".IRO",A11)),"Exclude", IF(ISNUMBER(SEARCH(".GOV",A11)),"Exclude", IF(ISNUMBER(SEARCH(".SBM",A11)),"Exclude", IF(ISNUMBER(SEARCH(".MDR",A11)),"Exclude", "Keep")))) -> Keep | C11: E1 | E11: E1-1 | F11: 16 c | H11: Financial resources allocated to action plan (OpEx) | I11: monetary | O11: Quantitative | Q11: In scope
A12: E1-1_06 | B12: =IF(ISNUMBER(SEARCH(".IRO",A12)),"Exclude", IF(ISNUMBER(SEARCH(".GOV",A12)),"Exclude", IF(ISNUMBER(SEARCH(".SBM",A12)),"Exclude", IF(ISNUMBER(SEARCH(".MDR",A12)),"Exclude", "Keep")))) -> Keep | C12: E1 | E12: E1-1 | F12: 16 c | H12: Financial resources allocated to action plan (CapEx) | I12: monetary | O12: Quantitative | Q12: In scope
A13: E1-1_07 | B13: =IF(ISNUMBER(SEARCH(".IRO",A13)),"Exclude", IF(ISNUMBER(SEARCH(".GOV",A13)),"Exclude", IF(ISNUMBER(SEARCH(".SBM",A13)),"Exclude", IF(ISNUMBER(SEARCH(".MDR",A13)),"Exclude", "Keep")))) -> Keep | C13: E1 | E13: E1-1 | F13: 16 d | G13: AR 3 | H13: Explanation of potential locked-in GHG emissions from key assets and products and of how locked-in GHG emissions may jeopardise achievement of GHG emission reduction targets and drive transition risk | I13: narrative | O13: Qualitative | Q13: In scope
A14: E1-1_08 | B14: =IF(ISNUMBER(SEARCH(".IRO",A14)),"Exclude", IF(ISNUMBER(SEARCH(".GOV",A14)),"Exclude", IF(ISNUMBER(SEARCH(".SBM",A14)),"Exclude", IF(ISNUMBER(SEARCH(".MDR",A14)),"Exclude", "Keep")))) -> Keep | C14: E1 | E14: E1-1 | F14: 16 e | G14: AR 4 | H14: Explanation of any objective or plans (CapEx, CapEx plans, OpEx) for aligning economic activities (revenues, CapEx, OpEx) with criteria established in Commission Delegated Regulation 2021/2139 | I14: narrative | J14: Conditional | O14: Qualitative | Q14: In scope
A15: E1-1_09 | B15: =IF(ISNUMBER(SEARCH(".IRO",A15)),"Exclude", IF(ISNUMBER(SEARCH(".GOV",A15)),"Exclude", IF(ISNUMBER(SEARCH(".SBM",A15)),"Exclude", IF(ISNUMBER(SEARCH(".MDR",A15)),"Exclude", "Keep")))) -> Keep | C15: E1 | E15: E1-1 | F15: 16 f | G15: AR 5 | H15: Significant CapEx for coal-related economic activities | I15: monetary | J15: Conditional | O15: Quantitative | Q15: In scope
A16: E1-1_10 | B16: =IF(ISNUMBER(SEARCH(".IRO",A16)),"Exclude", IF(ISNUMBER(SEARCH(".GOV",A16)),"Exclude", IF(ISNUMBER(SEARCH(".SBM",A16)),"Exclude", IF(ISNUMBER(SEARCH(".MDR",A16)),"Exclude", "Keep")))) -> Keep | C16: E1 | E16: E1-1 | F16: 16 f | G16: AR 5 | H16: Significant CapEx for oil-related economic activities | I16: monetary | J16: Conditional | O16: Quantitative | Q16: In scope
A17: E1-1_11 | B17: =IF(ISNUMBER(SEARCH(".IRO",A17)),"Exclude", IF(ISNUMBER(SEARCH(".GOV",A17)),"Exclude", IF(ISNUMBER(SEARCH(".SBM",A17)),"Exclude", IF(ISNUMBER(SEARCH(".MDR",A17)),"Exclude", "Keep")))) -> Keep | C17: E1 | E17: E1-1 | F17: 16 f | G17: AR 5 | H17: Significant CapEx for gas-related economic activities | I17: monetary | J17: Conditional | O17: Quantitative | Q17: In scope
A18: E1-1_12 | B18: =IF(ISNUMBER(SEARCH(".IRO",A18)),"Exclude", IF(ISNUMBER(SEARCH(".GOV",A18)),"Exclude", IF(ISNUMBER(SEARCH(".SBM",A18)),"Exclude", IF(ISNUMBER(SEARCH(".MDR",A18)),"Exclude", "Keep")))) -> Keep | C18: E1 | E18: E1-1 | F18: 16 g | H18: Undertaking is excluded from EU Paris-aligned Benchmarks | I18: semi-narrative | L18: PILLAR 3 + Benchmark | O18: Qualitative | Q18: In scope
A19: E1-1_13 | B19: =IF(ISNUMBER(SEARCH(".IRO",A19)),"Exclude", IF(ISNUMBER(SEARCH(".GOV",A19)),"Exclude", IF(ISNUMBER(SEARCH(".SBM",A19)),"Exclude", IF(ISNUMBER(SEARCH(".MDR",A19)),"Exclude", "Keep")))) -> Keep | C19: E1 | E19: E1-1 | F19: 16 h | H19: Explanation of how transition plan is embedded in and aligned with overall business strategy and financial planning | I19: narrative | O19: Qualitative | Q19: In scope
A20: E1-1_14 | B20: =IF(ISNUMBER(SEARCH(".IRO",A20)),"Exclude", IF(ISNUMBER(SEARCH(".GOV",A20)),"Exclude", IF(ISNUMBER(SEARCH(".SBM",A20)),"Exclude", IF(ISNUMBER(SEARCH(".MDR",A20)),"Exclude", "Keep")))) -> Keep | C20: E1 | E20: E1-1 | F20: 16 i | H20: Transition plan is approved by administrative, management and supervisory bodies | I20: semi-narrative | O20: Qualitative | Q20: In scope
A21: E1-1_15 | B21: =IF(ISNUMBER(SEARCH(".IRO",A21)),"Exclude", IF(ISNUMBER(SEARCH(".GOV",A21)),"Exclude", IF(ISNUMBER(SEARCH(".SBM",A21)),"Exclude", IF(ISNUMBER(SEARCH(".MDR",A21)),"Exclude", "Keep")))) -> Keep | C21: E1 | E21: E1-1 | F21: 16 j | H21: Explanation of progress in implementing transition plan | I21: narrative | O21: Qualitative | Q21: In scope
A22: E1-1_16 | B22: =IF(ISNUMBER(SEARCH(".IRO",A22)),"Exclude", IF(ISNUMBER(SEARCH(".GOV",A22)),"Exclude", IF(ISNUMBER(SEARCH(".SBM",A22)),"Exclude", IF(ISNUMBER(SEARCH(".MDR",A22)),"Exclude", "Keep")))) -> Keep | C22: E1 | E22: E1-1 | F22: 17 | H22: Date of adoption of transition plan for undertakings not having adopted transition plan yet | I22: gYear | J22: Conditional | O22: Qualitative | Q22: In scope
A23: E1.SBM-3_01 | B23: =IF(ISNUMBER(SEARCH(".IRO",A23)),"Exclude", IF(ISNUMBER(SEARCH(".GOV",A23)),"Exclude", IF(ISNUMBER(SEARCH(".SBM",A23)),"Exclude", IF(ISNUMBER(SEARCH(".MDR",A23)),"Exclude", "Keep")))) -> Exclude | C23: E1 | E23: E1.SBM-3 | F23: 18 | H23: Type of climate-related risk | I23: semi-narrative | O23: Qualitative | Q23: In scope
A24: E1.SBM-3_02 | B24: =IF(ISNUMBER(SEARCH(".IRO",A24)),"Exclude", IF(ISNUMBER(SEARCH(".GOV",A24)),"Exclude", IF(ISNUMBER(SEARCH(".SBM",A24)),"Exclude", IF(ISNUMBER(SEARCH(".MDR",A24)),"Exclude", "Keep")))) -> Exclude | C24: E1 | E24: E1.SBM-3 | F24: 19 a | G24: AR 6, AR 13 | H24: Description of scope of resilience analysis | I24: narrative | O24: Qualitative | Q24: In scope
A25: E1.SBM-3_03 | B25: =IF(ISNUMBER(SEARCH(".IRO",A25)),"Exclude", IF(ISNUMBER(SEARCH(".GOV",A25)),"Exclude", IF(ISNUMBER(SEARCH(".SBM",A25)),"Exclude", IF(ISNUMBER(SEARCH(".MDR",A25)),"Exclude", "Keep")))) -> Exclude | C25: E1 | E25: E1.SBM-3 | F25: 19 b | G25: AR 7a, AR 13 | H25: Disclosure of how resilience analysis has been conducted | I25: narrative | O25: Qualitative | Q25: In scope
A26: E1.SBM-3_04 | B26: =IF(ISNUMBER(SEARCH(".IRO",A26)),"Exclude", IF(ISNUMBER(SEARCH(".GOV",A26)),"Exclude", IF(ISNUMBER(SEARCH(".SBM",A26)),"Exclude", IF(ISNUMBER(SEARCH(".MDR",A26)),"Exclude", "Keep")))) -> Exclude | C26: E1 | E26: E1.SBM-3 | F26: 19 b | G26: AR 7a, AR 13 | H26: Disclosure of how resilience analysis has been conducted | I26: date | O26: Qualitative | Q26: In scope
A27: E1.SBM-3_05 | B27: =IF(ISNUMBER(SEARCH(".IRO",A27)),"Exclude", IF(ISNUMBER(SEARCH(".GOV",A27)),"Exclude", IF(ISNUMBER(SEARCH(".SBM",A27)),"Exclude", IF(ISNUMBER(SEARCH(".MDR",A27)),"Exclude", "Keep")))) -> Exclude | C27: E1 | E27: E1.SBM-3 | F27: AR 7b | H27: Time horizons applied for resilience analysis | I27: semi-narrative | O27: Qualitative | Q27: In scope
A28: E1.SBM-3_06 | B28: =IF(ISNUMBER(SEARCH(".IRO",A28)),"Exclude", IF(ISNUMBER(SEARCH(".GOV",A28)),"Exclude", IF(ISNUMBER(SEARCH(".SBM",A28)),"Exclude", IF(ISNUMBER(SEARCH(".MDR",A28)),"Exclude", "Keep")))) -> Exclude | C28: E1 | E28: E1.SBM-3 | F28: 19 c | G28: AR 8a, AR 13 | H28: Description of results of resilience analysis | I28: narrative | O28: Qualitative | Q28: In scope
A29: E1.SBM-3_07 | B29: =IF(ISNUMBER(SEARCH(".IRO",A29)),"Exclude", IF(ISNUMBER(SEARCH(".GOV",A29)),"Exclude", IF(ISNUMBER(SEARCH(".SBM",A29)),"Exclude", IF(ISNUMBER(SEARCH(".MDR",A29)),"Exclude", "Keep")))) -> Exclude | C29: E1 | E29: E1.SBM-3 | F29: AR 8 b | H29: Description of ability to adjust or adapt strategy and business model to climate change | I29: narrative | O29: Qualitative | Q29: In scope
A30: E1.IRO-1_01 | B30: =IF(ISNUMBER(SEARCH(".IRO",A30)),"Exclude", IF(ISNUMBER(SEARCH(".GOV",A30)),"Exclude", IF(ISNUMBER(SEARCH(".SBM",A30)),"Exclude", IF(ISNUMBER(SEARCH(".MDR",A30)),"Exclude", "Keep")))) -> Exclude | C30: E1 | E30: E1.IRO-1 | F30: 20 a, AR 9 | G30: AR 10 | H30: Description of process in relation to impacts on climate change | I30: narrative | O30: Qualitative | Q30: In scope
A31: E1.IRO-1_02 | B31: =IF(ISNUMBER(SEARCH(".IRO",A31)),"Exclude", IF(ISNUMBER(SEARCH(".GOV",A31)),"Exclude", IF(ISNUMBER(SEARCH(".SBM",A31)),"Exclude", IF(ISNUMBER(SEARCH(".MDR",A31)),"Exclude", "Keep")))) -> Exclude | C31: E1 | E31: E1.IRO-1 | F31: 20 b | G31: AR 13-AR 14 | H31: Description of process in relation to climate-related physical risks in own operations and along value chain | I31: narrative | O31: Qualitative | Q31: In scope
A32: E1.IRO-1_03 | B32: =IF(ISNUMBER(SEARCH(".IRO",A32)),"Exclude", IF(ISNUMBER(SEARCH(".GOV",A32)),"Exclude", IF(ISNUMBER(SEARCH(".SBM",A32)),"Exclude", IF(ISNUMBER(SEARCH(".MDR",A32)),"Exclude", "Keep")))) -> Exclude | C32: E1 | E32: E1.IRO-1 | F32: AR 11 a | G32: AR 13-AR 14 | H32: Climate-related hazards have been identified over short-, medium- and long-term time horizons | I32: semi-narrative | O32: Qualitative | Q32: In scope
A33: E1.IRO-1_04 | B33: =IF(ISNUMBER(SEARCH(".IRO",A33)),"Exclude", IF(ISNUMBER(SEARCH(".GOV",A33)),"Exclude", IF(ISNUMBER(SEARCH(".SBM",A33)),"Exclude", IF(ISNUMBER(SEARCH(".MDR",A33)),"Exclude", "Keep")))) -> Exclude | C33: E1 | E33: E1.IRO-1 | F33: AR 11 a | G33: AR 13-AR 14 | H33: Undertaking has screened whether assets and business activities may be exposed to climate-related hazards | I33: semi-narrative | O33: Qualitative | Q33: In scope
A34: E1.IRO-1_05 | B34: =IF(ISNUMBER(SEARCH(".IRO",A34)),"Exclude", IF(ISNUMBER(SEARCH(".GOV",A34)),"Exclude", IF(ISNUMBER(SEARCH(".SBM",A34)),"Exclude", IF(ISNUMBER(SEARCH(".MDR",A34)),"Exclude", "Keep")))) -> Exclude | C34: E1 | E34: E1.IRO-1 | F34: AR 11 b | G34: AR 13-AR 14 | H34: Short-, medium- and long-term time horizons have been defined | I34: semi-narrative | O34: Qualitative | Q34: In scope
A35: E1.IRO-1_06 | B35: =IF(ISNUMBER(SEARCH(".IRO",A35)),"Exclude", IF(ISNUMBER(SEARCH(".GOV",A35)),"Exclude", IF(ISNUMBER(SEARCH(".SBM",A35)),"Exclude", IF(ISNUMBER(SEARCH(".MDR",A35)),"Exclude", "Keep")))) -> Exclude | C35: E1 | E35: E1.IRO-1 | F35: AR 11 c | G35: AR 13-AR 14 | H35: Extent to which assets and business activities may be exposed and are sensitive to identified climate-related hazards has been assessed | I35: semi-narrative | O35: Qualitative | Q35: In scope
A36: E1.IRO-1_07 | B36: =IF(ISNUMBER(SEARCH(".IRO",A36)),"Exclude", IF(ISNUMBER(SEARCH(".GOV",A36)),"Exclude", IF(ISNUMBER(SEARCH(".SBM",A36)),"Exclude", IF(ISNUMBER(SEARCH(".MDR",A36)),"Exclude", "Keep")))) -> Exclude | C36: E1 | E36: E1.IRO-1 | F36: AR 11 d | G36: AR 13-AR 14 | H36: Identification of climate-related hazards and assessment of exposure and sensitivity are informed by high emissions climate scenarios | I36: semi-narrative | O36: Qualitative | Q36: In scope
A37: E1.IRO-1_08 | B37: =IF(ISNUMBER(SEARCH(".IRO",A37)),"Exclude", IF(ISNUMBER(SEARCH(".GOV",A37)),"Exclude", IF(ISNUMBER(SEARCH(".SBM",A37)),"Exclude", IF(ISNUMBER(SEARCH(".MDR",A37)),"Exclude", "Keep")))) -> Exclude | C37: E1 | E37: E1.IRO-1 | F37: 21 | G37: AR 13-AR 14 | H37: Explanation of how climate-related scenario analysis has been used to inform identification and assessment of physical risks over short, medium and long-term | I37: narrative | O37: Qualitative | Q37: In scope
A38: E1.IRO-1_09 | B38: =IF(ISNUMBER(SEARCH(".IRO",A38)),"Exclude", IF(ISNUMBER(SEARCH(".GOV",A38)),"Exclude", IF(ISNUMBER(SEARCH(".SBM",A38)),"Exclude", IF(ISNUMBER(SEARCH(".MDR",A38)),"Exclude", "Keep")))) -> Exclude | C38: E1 | E38: E1.IRO-1 | F38: 20 c | G38: AR 13-AR 14 | H38: Description of process in relation to climate-related transition risks and opportunities in own operations and along value chain | I38: narrative | O38: Qualitative | Q38: In scope
A39: E1.IRO-1_10 | B39: =IF(ISNUMBER(SEARCH(".IRO",A39)),"Exclude", IF(ISNUMBER(SEARCH(".GOV",A39)),"Exclude", IF(ISNUMBER(SEARCH(".SBM",A39)),"Exclude", IF(ISNUMBER(SEARCH(".MDR",A39)),"Exclude", "Keep")))) -> Exclude | C39: E1 | E39: E1.IRO-1 | F39: AR 12 a | G39: AR 13-AR 14 | H39: Transition events have been identified over short-, medium- and long-term time horizons | I39: semi-narrative | O39: Qualitative | Q39: In scope
A40: E1.IRO-1_11 | B40: =IF(ISNUMBER(SEARCH(".IRO",A40)),"Exclude", IF(ISNUMBER(SEARCH(".GOV",A40)),"Exclude", IF(ISNUMBER(SEARCH(".SBM",A40)),"Exclude", IF(ISNUMBER(SEARCH(".MDR",A40)),"Exclude", "Keep")))) -> Exclude | C40: E1 | E40: E1.IRO-1 | F40: AR 12 a | G40: AR 13-AR 14 | H40: Undertaking has screened whether assets and business activities may be exposed to transition events | I40: semi-narrative | O40: Qualitative | Q40: In scope
A41: E1.IRO-1_12 | B41: =IF(ISNUMBER(SEARCH(".IRO",A41)),"Exclude", IF(ISNUMBER(SEARCH(".GOV",A41)),"Exclude", IF(ISNUMBER(SEARCH(".SBM",A41)),"Exclude", IF(ISNUMBER(SEARCH(".MDR",A41)),"Exclude", "Keep")))) -> Exclude | C41: E1 | E41: E1.IRO-1 | F41: AR 12 b | G41: AR 13-AR 14 | H41: Extent to which assets and business activities may be exposed and are sensitive to identified transition events has been assessed | I41: semi-narrative | O41: Qualitative | Q41: In scope
A42: E1.IRO-1_13 | B42: =IF(ISNUMBER(SEARCH(".IRO",A42)),"Exclude", IF(ISNUMBER(SEARCH(".GOV",A42)),"Exclude", IF(ISNUMBER(SEARCH(".SBM",A42)),"Exclude", IF(ISNUMBER(SEARCH(".MDR",A42)),"Exclude", "Keep")))) -> Exclude | C42: E1 | E42: E1.IRO-1 | F42: AR 12 c | G42: AR 13-AR 14 | H42: Identification of transition events and assessment of exposure has been informed by climate-related scenario analysis | I42: semi-narrative | O42: Qualitative | Q42: In scope
A43: E1.IRO-1_14 | B43: =IF(ISNUMBER(SEARCH(".IRO",A43)),"Exclude", IF(ISNUMBER(SEARCH(".GOV",A43)),"Exclude", IF(ISNUMBER(SEARCH(".SBM",A43)),"Exclude", IF(ISNUMBER(SEARCH(".MDR",A43)),"Exclude", "Keep")))) -> Exclude | C43: E1 | E43: E1.IRO-1 | F43: AR 12 d | G43: AR 13-AR 14 | H43: Assets and business activities that are incompatible with or need significant efforts to be compatible with transition to climate-neutral economy have been identified | I43: semi-narrative | O43: Qualitative | Q43: In scope
A44: E1.IRO-1_15 | B44: =IF(ISNUMBER(SEARCH(".IRO",A44)),"Exclude", IF(ISNUMBER(SEARCH(".GOV",A44)),"Exclude", IF(ISNUMBER(SEARCH(".SBM",A44)),"Exclude", IF(ISNUMBER(SEARCH(".MDR",A44)),"Exclude", "Keep")))) -> Exclude | C44: E1 | E44: E1.IRO-1 | F44: 21 | G44: AR 13-AR 14 | H44: Explanation of how climate-related scenario analysis has been used to inform identification and assessment of transition risks and opportunities over short, medium and long-term | I44: narrative | O44: Qualitative | Q44: In scope
A45: E1.IRO-1_16 | B45: =IF(ISNUMBER(SEARCH(".IRO",A45)),"Exclude", IF(ISNUMBER(SEARCH(".GOV",A45)),"Exclude", IF(ISNUMBER(SEARCH(".SBM",A45)),"Exclude", IF(ISNUMBER(SEARCH(".MDR",A45)),"Exclude", "Keep")))) -> Exclude | C45: E1 | E45: E1.IRO-1 | F45: AR 15 | G45: AR 13-AR 14 | H45: Explanation of how climate scenarios used are compatible with critical climate-related assumptions made in financial statements | I45: narrative | O45: Qualitative | Q45: In scope
A46: E1.MDR-P_01-06 | B46: =IF(ISNUMBER(SEARCH(".IRO",A46)),"Exclude", IF(ISNUMBER(SEARCH(".GOV",A46)),"Exclude", IF(ISNUMBER(SEARCH(".SBM",A46)),"Exclude", IF(ISNUMBER(SEARCH(".MDR",A46)),"Exclude", "Keep")))) -> Exclude | C46: E1 | E46: E1-2 | F46: 24 | H46: Policies in place to manage its material impacts, risks and opportunities related to climate change mitigation and adaptation [see ESRS 2 MDR-P] | I46: MDR-P | O46: Qualitative | Q46: In scope
A47: E1-2_01 | B47: =IF(ISNUMBER(SEARCH(".IRO",A47)),"Exclude", IF(ISNUMBER(SEARCH(".GOV",A47)),"Exclude", IF(ISNUMBER(SEARCH(".SBM",A47)),"Exclude", IF(ISNUMBER(SEARCH(".MDR",A47)),"Exclude", "Keep")))) -> Keep | C47: E1 | E47: E1-2 | F47: 25 | G47: AR 16-AR18 | H47: Sustainability matters addressed by policy for climate change | I47: semi-narrative | O47: Qualitative | Q47: In scope
A48: E1.MDR-P_07-08 | B48: =IF(ISNUMBER(SEARCH(".IRO",A48)),"Exclude", IF(ISNUMBER(SEARCH(".GOV",A48)),"Exclude", IF(ISNUMBER(SEARCH(".SBM",A48)),"Exclude", IF(ISNUMBER(SEARCH(".MDR",A48)),"Exclude", "Keep")))) -> Exclude | C48: ESRS 2 | F48: 62 | H48: Disclosures to be reported in case the undertaking has not adopted policies | O48: Qualitative | Q48: In scope
A49: E1.MDR-A_01-12 | B49: =IF(ISNUMBER(SEARCH(".IRO",A49)),"Exclude", IF(ISNUMBER(SEARCH(".GOV",A49)),"Exclude", IF(ISNUMBER(SEARCH(".SBM",A49)),"Exclude", IF(ISNUMBER(SEARCH(".MDR",A49)),"Exclude", "Keep")))) -> Exclude | C49: E1 | E49: E1-3 | F49: 28 | H49: Actions and Resources related to climate change mitigation and adaptation [see ESRS 2 MDR-A] | I49: MDR-A | O49: Qualitative | Q49: In scope
A50: E1-3_01 | B50: =IF(ISNUMBER(SEARCH(".IRO",A50)),"Exclude", IF(ISNUMBER(SEARCH(".GOV",A50)),"Exclude", IF(ISNUMBER(SEARCH(".SBM",A50)),"Exclude", IF(ISNUMBER(SEARCH(".MDR",A50)),"Exclude", "Keep")))) -> Keep | C50: E1 | E50: E1-3 | F50: 29 a | H50: Decarbonisation lever type | I50: semi-narrative | O50: Qualitative | Q50: In scope
A51: E1-3_02 | B51: =IF(ISNUMBER(SEARCH(".IRO",A51)),"Exclude", IF(ISNUMBER(SEARCH(".GOV",A51)),"Exclude", IF(ISNUMBER(SEARCH(".SBM",A51)),"Exclude", IF(ISNUMBER(SEARCH(".MDR",A51)),"Exclude", "Keep")))) -> Keep | C51: E1 | E51: E1-3 | F51: AR19d | H51: Adaptation solution type | I51: semi-narrative | K51: V | O51: Qualitative | Q51: In scope
A52: E1-3_03 | B52: =IF(ISNUMBER(SEARCH(".IRO",A52)),"Exclude", IF(ISNUMBER(SEARCH(".GOV",A52)),"Exclude", IF(ISNUMBER(SEARCH(".SBM",A52)),"Exclude", IF(ISNUMBER(SEARCH(".MDR",A52)),"Exclude", "Keep")))) -> Keep | C52: E1 | E52: E1-3 | F52: 29 b | H52: Achieved GHG emission reductions | I52: ghgEmissions | O52: Qualitative | Q52: In scope
A53: E1-3_04 | B53: =IF(ISNUMBER(SEARCH(".IRO",A53)),"Exclude", IF(ISNUMBER(SEARCH(".GOV",A53)),"Exclude", IF(ISNUMBER(SEARCH(".SBM",A53)),"Exclude", IF(ISNUMBER(SEARCH(".MDR",A53)),"Exclude", "Keep")))) -> Keep | C53: E1 | E53: E1-3 | F53: 29 b | H53: Expected GHG emission reductions | I53: ghgEmissions | O53: Qualitative | Q53: In scope
A54: E1-3_05 | B54: =IF(ISNUMBER(SEARCH(".IRO",A54)),"Exclude", IF(ISNUMBER(SEARCH(".GOV",A54)),"Exclude", IF(ISNUMBER(SEARCH(".SBM",A54)),"Exclude", IF(ISNUMBER(SEARCH(".MDR",A54)),"Exclude", "Keep")))) -> Keep | C54: E1 | E54: E1-3 | F54: AR21 | H54: Explanation of extent to which ability to implement action depends on availability and allocation of resources | I54: narrative | O54: Qualitative | Q54: In scope
A55: E1-3_06 | B55: =IF(ISNUMBER(SEARCH(".IRO",A55)),"Exclude", IF(ISNUMBER(SEARCH(".GOV",A55)),"Exclude", IF(ISNUMBER(SEARCH(".SBM",A55)),"Exclude", IF(ISNUMBER(SEARCH(".MDR",A55)),"Exclude", "Keep")))) -> Keep | C55: E1 | E55: E1-3 | F55: 29 c i | G55: AR 20 | H55: Explanation of relationship of significant CapEx and OpEx required to implement actions taken or planned to relevant line items or notes in financial statements | I55: narrative/monetary | O55: Quantitative | Q55: In scope
A56: E1-3_07 | B56: =IF(ISNUMBER(SEARCH(".IRO",A56)),"Exclude", IF(ISNUMBER(SEARCH(".GOV",A56)),"Exclude", IF(ISNUMBER(SEARCH(".SBM",A56)),"Exclude", IF(ISNUMBER(SEARCH(".MDR",A56)),"Exclude", "Keep")))) -> Keep | C56: E1 | E56: E1-3 | F56: 29 c ii,16 c | G56: AR 22 | H56: Explanation of relationship of significant CapEx and OpEx required to implement actions taken or planned to key performance indicators required under Commission Delegated Regulation (EU) 2021/2178 | I56: narrative | O56: Qualitative | Q56: In scope
A57: E1-3_08 | B57: =IF(ISNUMBER(SEARCH(".IRO",A57)),"Exclude", IF(ISNUMBER(SEARCH(".GOV",A57)),"Exclude", IF(ISNUMBER(SEARCH(".SBM",A57)),"Exclude", IF(ISNUMBER(SEARCH(".MDR",A57)),"Exclude", "Keep")))) -> Keep | C57: E1 | E57: E1-3 | F57: 29 c iii,16 c | G57: AR 20 | H57: Explanation of relationship of significant CapEx and OpEx required to implement actions taken or planned to CapEx plan required by Commission Delegated Regulation (EU) 2021/2178 | I57: narrative | J57: Conditional | O57: Qualitative | Q57: In scope
A58: E1.MDR-A_13-14 | B58: =IF(ISNUMBER(SEARCH(".IRO",A58)),"Exclude", IF(ISNUMBER(SEARCH(".GOV",A58)),"Exclude", IF(ISNUMBER(SEARCH(".SBM",A58)),"Exclude", IF(ISNUMBER(SEARCH(".MDR",A58)),"Exclude", "Keep")))) -> Exclude | C58: ESRS 2 | F58: 62 | H58: Disclosure to be reported if the undertaking has not adopted actions | O58: Qualitative | Q58: In scope
A59: E1.MDR-T_01-13 | B59: =IF(ISNUMBER(SEARCH(".IRO",A59)),"Exclude", IF(ISNUMBER(SEARCH(".GOV",A59)),"Exclude", IF(ISNUMBER(SEARCH(".SBM",A59)),"Exclude", IF(ISNUMBER(SEARCH(".MDR",A59)),"Exclude", "Keep")))) -> Exclude | C59: E1 | E59: E1-4 | F59: 32 | H59: Tracking effectiveness of policies and actions through targets [see ESRS 2 MDR-T ] | I59: MDR-T | O59: Qualitative | Q59: In scope
A60: E1-4_01 | B60: =IF(ISNUMBER(SEARCH(".IRO",A60)),"Exclude", IF(ISNUMBER(SEARCH(".GOV",A60)),"Exclude", IF(ISNUMBER(SEARCH(".SBM",A60)),"Exclude", IF(ISNUMBER(SEARCH(".MDR",A60)),"Exclude", "Keep")))) -> Keep | C60: E1 | E60: E1-4 | F60: 33 | G60: AR 27-AR 29 | H60: Disclosure of whether and how GHG emissions reduction targets and (or) any other targets have been set to manage material climate-related impacts, risks and opportunities | I60: narrative | O60: Qualitative | Q60: In scope
A61: E1-4_02 | B61: =IF(ISNUMBER(SEARCH(".IRO",A61)),"Exclude", IF(ISNUMBER(SEARCH(".GOV",A61)),"Exclude", IF(ISNUMBER(SEARCH(".SBM",A61)),"Exclude", IF(ISNUMBER(SEARCH(".MDR",A61)),"Exclude", "Keep")))) -> Keep | C61: E1 | E61: E1-4 | F61: 34 a + 34 b | G61: AR 23-AR 24, AR 27-AR 29, AR31 | H61: Tables: Multiple Dimensions (baseline year and targets; GHG Types, Scope 3 Categories, Decarbonisation levers, entity-specific denominators for intensity value) | I61: Table | J61: Conditional | O61: Qualitative | Q61: In scope
A62: E1-4_03 | B62: =IF(ISNUMBER(SEARCH(".IRO",A62)),"Exclude", IF(ISNUMBER(SEARCH(".GOV",A62)),"Exclude", IF(ISNUMBER(SEARCH(".SBM",A62)),"Exclude", IF(ISNUMBER(SEARCH(".MDR",A62)),"Exclude", "Keep")))) -> Keep | C62: E1 | E62: E1-4 | F62: 34 a + 34 b | H62: Absolute value of total Greenhouse gas emissions reduction | I62: Table/ghgEmissions | J62: Conditional | L62: SFDR+PILLAR 3+ BENCHMARK | O62: Qualitative | Q62: In scope
A63: E1-4_04 | B63: =IF(ISNUMBER(SEARCH(".IRO",A63)),"Exclude", IF(ISNUMBER(SEARCH(".GOV",A63)),"Exclude", IF(ISNUMBER(SEARCH(".SBM",A63)),"Exclude", IF(ISNUMBER(SEARCH(".MDR",A63)),"Exclude", "Keep")))) -> Keep | C63: E1 | E63: E1-4 | F63: 34 a + 34 b | H63: Percentage of total Greenhouse gas emissions reduction (as of emissions of base year) | I63: Table/percent | J63: Conditional | L63: SFDR+PILLAR 3+ BENCHMARK | O63: Quantitative | Q63: In scope
A64: E1-4_05 | B64: =IF(ISNUMBER(SEARCH(".IRO",A64)),"Exclude", IF(ISNUMBER(SEARCH(".GOV",A64)),"Exclude", IF(ISNUMBER(SEARCH(".SBM",A64)),"Exclude", IF(ISNUMBER(SEARCH(".MDR",A64)),"Exclude", "Keep")))) -> Keep | C64: E1 | E64: E1-4 | F64: 34 a + 34 b | H64: Intensity value of total Greenhouse gas emissions reduction | I64: Table/decimal | J64: Conditional | L64: SFDR+PILLAR 3+ BENCHMARK | O64: Qualitative | Q64: In scope
A65: E1-4_06 | B65: =IF(ISNUMBER(SEARCH(".IRO",A65)),"Exclude", IF(ISNUMBER(SEARCH(".GOV",A65)),"Exclude", IF(ISNUMBER(SEARCH(".SBM",A65)),"Exclude", IF(ISNUMBER(SEARCH(".MDR",A65)),"Exclude", "Keep")))) -> Keep | C65: E1 | E65: E1-4 | F65: 34 a + 34 b | H65: Absolute value of Scope 1 Greenhouse gas emissions reduction | I65: Table/ghgEmissions | J65: Conditional | L65: SFDR+PILLAR 3+ BENCHMARK | O65: Qualitative | Q65: In scope
A66: E1-4_07 | B66: =IF(ISNUMBER(SEARCH(".IRO",A66)),"Exclude", IF(ISNUMBER(SEARCH(".GOV",A66)),"Exclude", IF(ISNUMBER(SEARCH(".SBM",A66)),"Exclude", IF(ISNUMBER(SEARCH(".MDR",A66)),"Exclude", "Keep")))) -> Keep | C66: E1 | E66: E1-4 | F66: 34 a + 34 b | H66: Percentage of Scope 1 Greenhouse gas emissions reduction (as of emissions of base year) | I66: Table/percent | J66: Conditional | L66: SFDR+PILLAR 3+ BENCHMARK | O66: Quantitative | Q66: In scope
A67: E1-4_08 | B67: =IF(ISNUMBER(SEARCH(".IRO",A67)),"Exclude", IF(ISNUMBER(SEARCH(".GOV",A67)),"Exclude", IF(ISNUMBER(SEARCH(".SBM",A67)),"Exclude", IF(ISNUMBER(SEARCH(".MDR",A67)),"Exclude", "Keep")))) -> Keep | C67: E1 | E67: E1-4 | F67: 34 a + 34 b | H67: Intensity value of Scope 1 Greenhouse gas emissions reduction | I67: Table/decimal | J67: Conditional | L67: SFDR+PILLAR 3+ BENCHMARK | O67: Qualitative | Q67: In scope
A68: E1-4_09 | B68: =IF(ISNUMBER(SEARCH(".IRO",A68)),"Exclude", IF(ISNUMBER(SEARCH(".GOV",A68)),"Exclude", IF(ISNUMBER(SEARCH(".SBM",A68)),"Exclude", IF(ISNUMBER(SEARCH(".MDR",A68)),"Exclude", "Keep")))) -> Keep | C68: E1 | E68: E1-4 | F68: 34 a + 34 b | H68: Absolute value of location-based Scope 2 Greenhouse gas emissions reduction | I68: Table/ghgEmissions | J68: Conditional | L68: SFDR+PILLAR 3+ BENCHMARK | O68: Qualitative | Q68: In scope
A69: E1-4_10 | B69: =IF(ISNUMBER(SEARCH(".IRO",A69)),"Exclude", IF(ISNUMBER(SEARCH(".GOV",A69)),"Exclude", IF(ISNUMBER(SEARCH(".SBM",A69)),"Exclude", IF(ISNUMBER(SEARCH(".MDR",A69)),"Exclude", "Keep")))) -> Keep | C69: E1 | E69: E1-4 | F69: 34 a + 34 b | H69: Percentage of location-based Scope 2 Greenhouse gas emissions reduction (as of emissions of base year) | I69: Table/percent | J69: Conditional | L69: SFDR+PILLAR 3+ BENCHMARK | O69: Quantitative | Q69: In scope
A70: E1-4_11 | B70: =IF(ISNUMBER(SEARCH(".IRO",A70)),"Exclude", IF(ISNUMBER(SEARCH(".GOV",A70)),"Exclude", IF(ISNUMBER(SEARCH(".SBM",A70)),"Exclude", IF(ISNUMBER(SEARCH(".MDR",A70)),"Exclude", "Keep")))) -> Keep | C70: E1 | E70: E1-4 | F70: 34 a + 34 b | H70: Intensity value of location-based Scope 2 Greenhouse gas emissions reduction | I70: Table/decimal | J70: Conditional | L70: SFDR+PILLAR 3+ BENCHMARK | O70: Qualitative | Q70: In scope
A71: E1-4_12 | B71: =IF(ISNUMBER(SEARCH(".IRO",A71)),"Exclude", IF(ISNUMBER(SEARCH(".GOV",A71)),"Exclude", IF(ISNUMBER(SEARCH(".SBM",A71)),"Exclude", IF(ISNUMBER(SEARCH(".MDR",A71)),"Exclude", "Keep")))) -> Keep | C71: E1 | E71: E1-4 | F71: 34 a + 34 b | H71: Absolute value of market-based Scope 2 Greenhouse gas emissions reduction | I71: Table/ghgEmissions | J71: Conditional | L71: SFDR+PILLAR 3+ BENCHMARK | O71: Qualitative | Q71: In scope
A72: E1-4_13 | B72: =IF(ISNUMBER(SEARCH(".IRO",A72)),"Exclude", IF(ISNUMBER(SEARCH(".GOV",A72)),"Exclude", IF(ISNUMBER(SEARCH(".SBM",A72)),"Exclude", IF(ISNUMBER(SEARCH(".MDR",A72)),"Exclude", "Keep")))) -> Keep | C72: E1 | E72: E1-4 | F72: 34 a + 34 b | H72: Percentage of market-based Scope 2 Greenhouse gas emissions reduction (as of emissions of base year) | I72: Table/percent | J72: Conditional | L72: SFDR+PILLAR 3+ BENCHMARK | O72: Quantitative | Q72: In scope
A73: E1-4_14 | B73: =IF(ISNUMBER(SEARCH(".IRO",A73)),"Exclude", IF(ISNUMBER(SEARCH(".GOV",A73)),"Exclude", IF(ISNUMBER(SEARCH(".SBM",A73)),"Exclude", IF(ISNUMBER(SEARCH(".MDR",A73)),"Exclude", "Keep")))) -> Keep | C73: E1 | E73: E1-4 | F73: 34 a + 34 b | H73: Intensity value of market-based Scope 2 Greenhouse gas emissions reduction | I73: Table/decimal | J73: Conditional | L73: SFDR+PILLAR 3+ BENCHMARK | O73: Qualitative | Q73: In scope
... A76: E1-4_17 | B76: =IF(ISNUMBER(SEARCH(".IRO",A76)),"Exclude", IF(ISNUMBER(SEARCH(".GOV",A76)),"Exclude", IF(ISNUMBER(SEARCH(".SBM",A76)),"Exclude", IF(ISNUMBER(SEARCH(".MDR",A76)),"Exclude", "Keep")))) -> Keep | C76: E1 | E76: E1-4 | F76: 34 a + 34 b | H76: Intensity value of Scope 3 Greenhouse gas emissions reduction | I76: Table/decimal | J76: Conditional | L76: SFDR+PILLAR 3+ BENCHMARK | O76: Qualitative | Q76: In scope
A77: E1-4_18 | B77: =IF(ISNUMBER(SEARCH(".IRO",A77)),"Exclude", IF(ISNUMBER(SEARCH(".GOV",A77)),"Exclude", IF(ISNUMBER(SEARCH(".SBM",A77)),"Exclude", IF(ISNUMBER(SEARCH(".MDR",A77)),"Exclude", "Keep")))) -> Keep | C77: E1 | E77: E1-4 | F77: 34 b | H77: Explanation of how consistency of GHG emission reduction targets with GHG inventory boundaries has been ensured | I77: narrative | O77: Qualitative | Q77: In scope
A78: E1-4_19 | B78: =IF(ISNUMBER(SEARCH(".IRO",A78)),"Exclude", IF(ISNUMBER(SEARCH(".GOV",A78)),"Exclude", IF(ISNUMBER(SEARCH(".SBM",A78)),"Exclude", IF(ISNUMBER(SEARCH(".MDR",A78)),"Exclude", "Keep")))) -> Keep | C78: E1 | E78: E1-4 | F78: 34 c | H78: Disclosure of past progress made in meeting target before current base year | I78: narrative | K78: V | O78: Qualitative | Q78: In scope
A79: E1-4_20 | B79: =IF(ISNUMBER(SEARCH(".IRO",A79)),"Exclude", IF(ISNUMBER(SEARCH(".GOV",A79)),"Exclude", IF(ISNUMBER(SEARCH(".SBM",A79)),"Exclude", IF(ISNUMBER(SEARCH(".MDR",A79)),"Exclude", "Keep")))) -> Keep | C79: E1 | E79: E1-4 | F79: AR 25 a | H79: Description of how it has been ensured that baseline value is representative in terms of activities covered and influences from external factors | I79: narrative | O79: Qualitative | Q79: In scope
A80: E1-4_21 | B80: =IF(ISNUMBER(SEARCH(".IRO",A80)),"Exclude", IF(ISNUMBER(SEARCH(".GOV",A80)),"Exclude", IF(ISNUMBER(SEARCH(".SBM",A80)),"Exclude", IF(ISNUMBER(SEARCH(".MDR",A80)),"Exclude", "Keep")))) -> Keep | C80: E1 | E80: E1-4 | F80: AR 25 b | H80: Description of how new baseline value affects new target, its achievement and presentation of progress over time | I80: narrative | O80: Qualitative | Q80: In scope
A81: E1-4_22 | B81: =IF(ISNUMBER(SEARCH(".IRO",A81)),"Exclude", IF(ISNUMBER(SEARCH(".GOV",A81)),"Exclude", IF(ISNUMBER(SEARCH(".SBM",A81)),"Exclude", IF(ISNUMBER(SEARCH(".MDR",A81)),"Exclude", "Keep")))) -> Keep | C81: E1 | E81: E1-4 | F81: 34 e, 16 a | G81: AR 26 | H81: GHG emission reduction target is science based and compatible with limiting global warming to one and half degrees Celsius | I81: semi-narrative | O81: Qualitative | Q81: In scope
A82: E1-4_23 | B82: =IF(ISNUMBER(SEARCH(".IRO",A82)),"Exclude", IF(ISNUMBER(SEARCH(".GOV",A82)),"Exclude", IF(ISNUMBER(SEARCH(".SBM",A82)),"Exclude", IF(ISNUMBER(SEARCH(".MDR",A82)),"Exclude", "Keep")))) -> Keep | C82: E1 | E82: E1-4 | F82: 34 f, 16 b | G82: AR 30 | H82: Description of expected decarbonisation levers and their overall quantitative contributions to achieve GHG emission reduction target | I82: narrative | O82: Qualitative | Q82: In scope
A83: E1-4_24 | B83: =IF(ISNUMBER(SEARCH(".IRO",A83)),"Exclude", IF(ISNUMBER(SEARCH(".GOV",A83)),"Exclude", IF(ISNUMBER(SEARCH(".SBM",A83)),"Exclude", IF(ISNUMBER(SEARCH(".MDR",A83)),"Exclude", "Keep")))) -> Keep | C83: E1 | E83: E1-4 | F83: AR 30 c | H83: Diverse range of climate scenarios have been considered to detect relevant environmental, societal, technology, market and policy-related developments and determine decarbonisation levers | I83: narrative | O83: Qualitative | Q83: In scope
A84: E1.MDR-T_14-19 | B84: =IF(ISNUMBER(SEARCH(".IRO",A84)),"Exclude", IF(ISNUMBER(SEARCH(".GOV",A84)),"Exclude", IF(ISNUMBER(SEARCH(".SBM",A84)),"Exclude", IF(ISNUMBER(SEARCH(".MDR",A84)),"Exclude", "Keep")))) -> Exclude | C84: ESRS 2 | E84: E1-4 | F84: 81 | H84: Disclosure to be reported if the undertaking has not set any measurable outcome-oriented targets | O84: Qualitative | Q84: In scope
A85: E1-5_01 | B85: =IF(ISNUMBER(SEARCH(".IRO",A85)),"Exclude", IF(ISNUMBER(SEARCH(".GOV",A85)),"Exclude", IF(ISNUMBER(SEARCH(".SBM",A85)),"Exclude", IF(ISNUMBER(SEARCH(".MDR",A85)),"Exclude", "Keep")))) -> Keep | C85: E1 | E85: E1-5 | F85: 37 | G85: AR 35 | H85: Total energy consumption related to own operations | I85: energy | L85: SFDR | O85: Qualitative | Q85: In scope
A86: E1-5_02 | B86: =IF(ISNUMBER(SEARCH(".IRO",A86)),"Exclude", IF(ISNUMBER(SEARCH(".GOV",A86)),"Exclude", IF(ISNUMBER(SEARCH(".SBM",A86)),"Exclude", IF(ISNUMBER(SEARCH(".MDR",A86)),"Exclude", "Keep")))) -> Keep | C86: E1 | E86: E1-5 | F86: 37 a | G86: AR 33, AR 32 | H86: Total energy consumption from fossil sources | I86: energy | L86: SFDR | O86: Qualitative | Q86: In scope
A87: E1-5_03 | B87: =IF(ISNUMBER(SEARCH(".IRO",A87)),"Exclude", IF(ISNUMBER(SEARCH(".GOV",A87)),"Exclude", IF(ISNUMBER(SEARCH(".SBM",A87)),"Exclude", IF(ISNUMBER(SEARCH(".MDR",A87)),"Exclude", "Keep")))) -> Keep | C87: E1 | E87: E1-5 | F87: 37 b | H87: Total energy consumption from nuclear sources | I87: energy | L87: SFDR | O87: Qualitative | Q87: In scope
A88: E1-5_04 | B88: =IF(ISNUMBER(SEARCH(".IRO",A88)),"Exclude", IF(ISNUMBER(SEARCH(".GOV",A88)),"Exclude", IF(ISNUMBER(SEARCH(".SBM",A88)),"Exclude", IF(ISNUMBER(SEARCH(".MDR",A88)),"Exclude", "Keep")))) -> Keep | C88: E1 | E88: E1-5 | F88: AR 34 | H88: Percentage of energy consumption from nuclear sources in total energy consumption | I88: percent | O88: Quantitative | Q88: In scope
A89: E1-5_05 | B89: =IF(ISNUMBER(SEARCH(".IRO",A89)),"Exclude", IF(ISNUMBER(SEARCH(".GOV",A89)),"Exclude", IF(ISNUMBER(SEARCH(".SBM",A89)),"Exclude", IF(ISNUMBER(SEARCH(".MDR",A89)),"Exclude", "Keep")))) -> Keep | C89: E1 | E89: E1-5 | F89: 37 c | H89: Total energy consumption from renewable sources | I89: energy | L89: SFDR | O89: Qualitative | Q89: In scope
A90: E1-5_06 | B90: =IF(ISNUMBER(SEARCH(".IRO",A90)),"Exclude", IF(ISNUMBER(SEARCH(".GOV",A90)),"Exclude", IF(ISNUMBER(SEARCH(".SBM",A90)),"Exclude", IF(ISNUMBER(SEARCH(".MDR",A90)),"Exclude", "Keep")))) -> Keep | C90: E1 | E90: E1-5 | F90: 37 c i | H90: Fuel consumption from renewable sources | I90: energy | L90: SFDR | O90: Qualitative | Q90: In scope
A91: E1-5_07 | B91: =IF(ISNUMBER(SEARCH(".IRO",A91)),"Exclude", IF(ISNUMBER(SEARCH(".GOV",A91)),"Exclude", IF(ISNUMBER(SEARCH(".SBM",A91)),"Exclude", IF(ISNUMBER(SEARCH(".MDR",A91)),"Exclude", "Keep")))) -> Keep | C91: E1 | E91: E1-5 | F91: 37 c ii | H91: Consumption of purchased or acquired electricity, heat, steam, and cooling from renewable sources | I91: energy | L91: SFDR | O91: Qualitative | Q91: In scope
A92: E1-5_08 | B92: =IF(ISNUMBER(SEARCH(".IRO",A92)),"Exclude", IF(ISNUMBER(SEARCH(".GOV",A92)),"Exclude", IF(ISNUMBER(SEARCH(".SBM",A92)),"Exclude", IF(ISNUMBER(SEARCH(".MDR",A92)),"Exclude", "Keep")))) -> Keep | C92: E1 | E92: E1-5 | F92: 37 c iii | H92: Consumption of self-generated non-fuel renewable energy | I92: energy | L92: SFDR | O92: Qualitative | Q92: In scope
A93: E1-5_09 | B93: =IF(ISNUMBER(SEARCH(".IRO",A93)),"Exclude", IF(ISNUMBER(SEARCH(".GOV",A93)),"Exclude", IF(ISNUMBER(SEARCH(".SBM",A93)),"Exclude", IF(ISNUMBER(SEARCH(".MDR",A93)),"Exclude", "Keep")))) -> Keep | C93: E1 | E93: E1-5 | F93: AR 34 | H93: Percentage of renewable sources in total energy consumption | I93: percent | O93: Quantitative | Q93: In scope
A94: E1-5_10 | B94: =IF(ISNUMBER(SEARCH(".IRO",A94)),"Exclude", IF(ISNUMBER(SEARCH(".GOV",A94)),"Exclude", IF(ISNUMBER(SEARCH(".SBM",A94)),"Exclude", IF(ISNUMBER(SEARCH(".MDR",A94)),"Exclude", "Keep")))) -> Keep | C94: E1 | E94: E1-5 | F94: 38 a | G94: AR 33 | H94: Fuel consumption from coal and coal products | I94: energy | J94: Conditional | L94: SFDR | O94: Qualitative | Q94: In scope
A95: E1-5_11 | B95: =IF(ISNUMBER(SEARCH(".IRO",A95)),"Exclude", IF(ISNUMBER(SEARCH(".GOV",A95)),"Exclude", IF(ISNUMBER(SEARCH(".SBM",A95)),"Exclude", IF(ISNUMBER(SEARCH(".MDR",A95)),"Exclude", "Keep")))) -> Keep | C95: E1 | E95: E1-5 | F95: 38 b | G95: AR 33 | H95: Fuel consumption from crude oil and petroleum products | I95: energy | J95: Conditional | L95: SFDR | O95: Qualitative | Q95: In scope
A96: E1-5_12 | B96: =IF(ISNUMBER(SEARCH(".IRO",A96)),"Exclude", IF(ISNUMBER(SEARCH(".GOV",A96)),"Exclude", IF(ISNUMBER(SEARCH(".SBM",A96)),"Exclude", IF(ISNUMBER(SEARCH(".MDR",A96)),"Exclude", "Keep")))) -> Keep | C96: E1 | E96: E1-5 | F96: 38 c | G96: AR 33 | H96: Fuel consumption from natural gas | I96: energy | J96: Conditional | L96: SFDR | O96: Qualitative | Q96: In scope
A97: E1-5_13 | B97: =IF(ISNUMBER(SEARCH(".IRO",A97)),"Exclude", IF(ISNUMBER(SEARCH(".GOV",A97)),"Exclude", IF(ISNUMBER(SEARCH(".SBM",A97)),"Exclude", IF(ISNUMBER(SEARCH(".MDR",A97)),"Exclude", "Keep")))) -> Keep | C97: E1 | E97: E1-5 | F97: 38 d | G97: AR 33 | H97: Fuel consumption from other fossil sources | I97: energy | J97: Conditional | L97: SFDR | O97: Qualitative | Q97: In scope
A98: E1-5_14 | B98: =IF(ISNUMBER(SEARCH(".IRO",A98)),"Exclude", IF(ISNUMBER(SEARCH(".GOV",A98)),"Exclude", IF(ISNUMBER(SEARCH(".SBM",A98)),"Exclude", IF(ISNUMBER(SEARCH(".MDR",A98)),"Exclude", "Keep")))) -> Keep | C98: E1 | E98: E1-5 | F98: 38 e | G98: AR 33 | H98: Consumption of purchased or acquired electricity, heat, steam, or cooling from fossil sources | I98: energy | J98: Conditional | L98: SFDR | O98: Qualitative | Q98: In scope
A99: E1-5_15 | B99: =IF(ISNUMBER(SEARCH(".IRO",A99)),"Exclude", IF(ISNUMBER(SEARCH(".GOV",A99)),"Exclude", IF(ISNUMBER(SEARCH(".SBM",A99)),"Exclude", IF(ISNUMBER(SEARCH(".MDR",A99)),"Exclude", "Keep")))) -> Keep | C99: E1 | E99: E1-5 | F99: AR 34 | H99: Percentage of fossil sources in total energy consumption | I99: percent | J99: Conditional | O99: Quantitative | Q99: In scope
A100: E1-5_16 | B100: =IF(ISNUMBER(SEARCH(".IRO",A100)),"Exclude", IF(ISNUMBER(SEARCH(".GOV",A100)),"Exclude", IF(ISNUMBER(SEARCH(".SBM",A100)),"Exclude", IF(ISNUMBER(SEARCH(".MDR",A100)),"Exclude", "Keep")))) -> Keep | C100: E1 | E100: E1-5 | F100: 39 | H100: Non-renewable energy production | I100: energy | J100: Conditional | O100: Qualitative | Q100: In scope
A101: E1-5_17 | B101: =IF(ISNUMBER(SEARCH(".IRO",A101)),"Exclude", IF(ISNUMBER(SEARCH(".GOV",A101)),"Exclude", IF(ISNUMBER(SEARCH(".SBM",A101)),"Exclude", IF(ISNUMBER(SEARCH(".MDR",A101)),"Exclude", "Keep")))) -> Keep | C101: E1 | E101: E1-5 | F101: 39 | H101: Renewable energy production | I101: energy | J101: Conditional | O101: Qualitative | Q101: In scope
A102: E1-5_18 | B102: =IF(ISNUMBER(SEARCH(".IRO",A102)),"Exclude", IF(ISNUMBER(SEARCH(".GOV",A102)),"Exclude", IF(ISNUMBER(SEARCH(".SBM",A102)),"Exclude", IF(ISNUMBER(SEARCH(".MDR",A102)),"Exclude", "Keep")))) -> Keep | C102: E1 | E102: E1-5 | F102: 40 | G102: AR 36 | H102: Energy intensity from activities in high climate impact sectors (total energy consumption per net revenue) | I102: percent | J102: Conditional | L102: SFDR | O102: Quantitative | Q102: In scope
A103: E1-5_19 | B103: =IF(ISNUMBER(SEARCH(".IRO",A103)),"Exclude", IF(ISNUMBER(SEARCH(".GOV",A103)),"Exclude", IF(ISNUMBER(SEARCH(".SBM",A103)),"Exclude", IF(ISNUMBER(SEARCH(".MDR",A103)),"Exclude", "Keep")))) -> Keep | C103: E1 | E103: E1-5 | F103: 41 | H103: Total energy consumption from activities in high climate impact sectors | I103: Intensity | J103: Conditional | L103: SFDR | O103: Qualitative | Q103: In scope
...

Sheet Mapping_ALLStacked
A1: Company | B1: Topic | C1: DR | D1: Description
A2: {=_xlfn.VSTACK(Bolton_Mapping!A2:D47, Espersen_Mapping!A2:D57, Mowi_Mapping!A2:D50, Nomad_Mapping!A2:D97, Profand_Mapping!A2:D77)} -> Bolton | B2: E1 | C2: E1-1 | D2: Transition plan for climate change mitigation
A3: Bolton | B3: E1 | C3: E1-2 | D3: Policies related to climate change mitigation and adaptation
A4: Bolton | B4: E1 | C4: E1-3 | D4: Actions and resources in relation to climate change policies
A5: Bolton | B5: E1 | C5: E1-4 | D5: Targets related to climate change mitigation and adaptation
A6: Bolton | B6: E1 | C6: E1-5 | D6: Energy consumption and mix
A7: Bolton | B7: E1 | C7: E1-6 | D7: Gross Scopes 1,2, 3 and Total GHG emissions
A8: Bolton | B8: E3 | C8: E3-1 | D8: Policies related to water and marine resources
A9: Bolton | B9: E3 | C9: E3-2 | D9: Actions and resources related to water and marine resources
A10: Bolton | B10: E3 | C10: E3-3 | D10: Targets related to water and marine resources
A11: Bolton | B11: E3 | C11: E3-4 | D11: Water consumption
A12: Bolton | B12: E5 | C12: E5-1 | D12: Policies related to resource use and circular economy
A13: Bolton | B13: E5 | C13: E5-2 | D13: Actions and resources related to resource use and circular economy
A14: Bolton | B14: E5 | C14: E5-3 | D14: Targets related to resource use and circular economy
... A324: Profand | B324: S4 | C324: S4-4 | D324: Substantiated complaints regarding breaches of customer privacy and loss of customer data

Sheet DP_Mapping
A1: Source_Datapoint_ID | B1: Source_Datapoint_Label | C1: Matched_ESRS_Standard | D1: Matched_Disclosure_Requirement | E1: Matched_Official_Datapoint_ID | F1: Matched_Official_Datapoint_Name | G1: Match_Type | H1: Match_Confidence | I1: Reviewer_Check_Needed | J1: Mapping_Rationale | K1: Candidate_2_ID | L1: Candidate_2_Name | M1: Candidate_2_Score
A2: e1_E1-1_Climate_governance_committee | B2: E1-1 Climate governance committee | C2: E1 | D2: E1-1 | E2: E1-1_01 | F2: =_xlfn.XLOOKUP(Table8[[#This Row],[Matched_Official_Datapoint_ID]], ESRS_MASTER!A:A, ESRS_MASTER!H:H, 0,0) -> Disclosure of transition plan for climate change mitigation | G2: Exact / near-exact DR-level semantic match | H2: High | I2: No | J2: DR cue detected: E1-1; Standard cue detected: E1; shared terms: climate, e1; score=0.82; runner-up gap=0.02 | K2: E1-1_02 | L2: Explanation of how targets are compatible with limiting of global warming to one and half degrees Celsius in line with Paris Agreement | M2: 0.79
A3: e1_E1-1_Climate_transition_plan_existe | B3: E1-1 Climate transition plan existe | C3: E1 | D3: E1-1 | E3: E1-1_01 | F3: =_xlfn.XLOOKUP(Table8[[#This Row],[Matched_Official_Datapoint_ID]], ESRS_MASTER!A:A, ESRS_MASTER!H:H, 0,0) -> Disclosure of transition plan for climate change mitigation | G3: Exact / near-exact DR-level semantic match | H3: High | I3: No | J3: DR cue detected: E1-1; Standard cue detected: E1; shared terms: climate, e1, plan, transition; score=0.95; runner-up gap=0.06 | K3: E1-1_13 | L3: Explanation of how transition plan is embedded in and aligned with overall business strategy and financial planning | M3: 0.90
A4: e1_E1-1_Decarbonisation_levers_identif | B4: E1-1 Decarbonisation levers identif | C4: E1 | D4: E1-1 | E4: E1-1_03 | F4: =_xlfn.XLOOKUP(Table8[[#This Row],[Matched_Official_Datapoint_ID]], ESRS_MASTER!A:A, ESRS_MASTER!H:H, 0,0) -> Disclosure of decarbonisation levers and key action | G4: Exact / near-exact DR-level semantic match | H4: High | I4: No | J4: DR cue detected: E1-1; Standard cue detected: E1; shared terms: decarbonisation, e1, levers; score=0.90; runner-up gap=0.01 | K4: E1-1_01 | L4: Disclosure of transition plan for climate change mitigation | M4: 0.89
A5: e1_E1-1_Netzero_commitment | B5: E1-1 Netzero commitment | C5: E1 | D5: E1-1 | E5: E1-1_01 | F5: =_xlfn.XLOOKUP(Table8[[#This Row],[Matched_Official_Datapoint_ID]], ESRS_MASTER!A:A, ESRS_MASTER!H:H, 0,0) -> Disclosure of transition plan for climate change mitigation | G5: Exact / near-exact DR-level semantic match | H5: High | I5: No | J5: DR cue detected: E1-1; Standard cue detected: E1; shared terms: climate, e1; score=0.84; runner-up gap=0.04 | K5: E1-1_07 | L5: Explanation of potential locked-in GHG emissions from key assets and products and of how locked-in GHG emissions may jeopardise achievement of GHG emission reduction targets and drive transition risk | M5: 0.80
A6: e1_E1-1_Paris_alignment_commitment | B6: E1-1 Paris alignment commitment | C6: E1 | D6: E1-1 | E6: E1-1_02 | F6: =_xlfn.XLOOKUP(Table8[[#This Row],[Matched_Official_Datapoint_ID]], ESRS_MASTER!A:A, ESRS_MASTER!H:H, 0,0) -> Explanation of how targets are compatible with limiting of global warming to one and half degrees Celsius in line with Paris Agreement | G6: Exact / near-exact DR-level semantic match | H6: High | I6: No | J6: DR cue detected: E1-1; Standard cue detected: E1; shared terms: agreement, e1, paris; score=0.86; runner-up gap=0.01 | K6: E1-1_12 | L6: Undertaking is excluded from EU Paris-aligned Benchmarks | M6: 0.85
A7: e1_E1-1_SBTi_commitment | B7: E1-1 SBTi commitment | C7: E1 | D7: E1-1 | E7: E1-1_07 | F7: =_xlfn.XLOOKUP(Table8[[#This Row],[Matched_Official_Datapoint_ID]], ESRS_MASTER!A:A, ESRS_MASTER!H:H, 0,0) -> Explanation of potential locked-in GHG emissions from key assets and products and of how locked-in GHG emissions may jeopardise achievement of GHG emission reduction targets and drive transition risk | G7: Exact / near-exact DR-level semantic match | H7: High | I7: No | J7: DR cue detected: E1-1; Standard cue detected: E1; shared terms: e1, emission, reduction, targets; score=0.85; runner-up gap=0.02 | K7: E1-1_02 | L7: Explanation of how targets are compatible with limiting of global warming to one and half degrees Celsius in line with Paris Agreement | M7: 0.83
A8: e1_E1-1_Transition_plan_for_climate_ch | B8: E1-1 Transition plan for climate ch | C8: E1 | D8: E1-1 | E8: E1-1_01 | F8: =_xlfn.XLOOKUP(Table8[[#This Row],[Matched_Official_Datapoint_ID]], ESRS_MASTER!A:A, ESRS_MASTER!H:H, 0,0) -> Disclosure of transition plan for climate change mitigation | G8: Exact / near-exact DR-level semantic match | H8: High | I8: No | J8: DR cue detected: E1-1; Standard cue detected: E1; shared terms: change, climate, e1, mitigation, plan, transition; score=1.03; runner-up gap=0.12 | K8: E1-1_15 | L8: Explanation of progress in implementing transition plan | M8: 0.91
A9: e1_E1-1/E1-3_Estimated_reduction_per_lever | B9: E1-1/E1-3 Estimated reduction per lever | C9: E1 | D9: E1-1 | E9: E1-1_07 | F9: =_xlfn.XLOOKUP(Table8[[#This Row],[Matched_Official_Datapoint_ID]], ESRS_MASTER!A:A, ESRS_MASTER!H:H, 0,0) -> Explanation of potential locked-in GHG emissions from key assets and products and of how locked-in GHG emissions may jeopardise achievement of GHG emission reduction targets and drive transition risk | G9: Exact / near-exact DR-level semantic match | H9: High | I9: No | J9: DR cue detected: E1-1; Standard cue detected: E1; shared terms: e1, emissions, ghg, reduction, transition; score=0.89; runner-up gap=0.02 | K9: E1-1_01 | L9: Disclosure of transition plan for climate change mitigation | M9: 0.87
A10: e1_E1-1/E1-9_TCFDaligned_climate_risk_asses | B10: E1-1/E1-9 TCFDaligned climate risk asses | C10: E1 | D10: E1-1 | E10: E1-1_13 | F10: =_xlfn.XLOOKUP(Table8[[#This Row],[Matched_Official_Datapoint_ID]], ESRS_MASTER!A:A, ESRS_MASTER!H:H, 0,0) -> Explanation of how transition plan is embedded in and aligned with overall business strategy and financial planning | G10: Exact / near-exact DR-level semantic match | H10: High | I10: No | J10: DR cue detected: E1-1; Standard cue detected: E1; shared terms: aligned, e1, is, strategy; score=0.88; runner-up gap=0.02 | K10: E1-1_12 | L10: Undertaking is excluded from EU Paris-aligned Benchmarks | M10: 0.87
A11: e1_E1-2_Climate_and_Environmental_Poli | B11: E1-2 Climate and Environmental Poli | C11: E1 | D11: E1-2 | E11: E1-2_01 | F11: =_xlfn.XLOOKUP(Table8[[#This Row],[Matched_Official_Datapoint_ID]], ESRS_MASTER!A:A, ESRS_MASTER!H:H, 0,0) -> Sustainability matters addressed by policy for climate change | G11: Exact / near-exact DR-level semantic match | H11: High | I11: No | J11: DR cue detected: E1-2; Standard cue detected: E1; shared terms: climate, e1, policy; score=0.84; runner-up gap=0.05 | K11: E1.MDR-P_01-06 | L11: Policies in place to manage its material impacts, risks and opportunities related to climate change mitigation and adaptation [see ESRS 2 MDR-P] | M11: 0.78
A12: e1_E1-2_Climaterelated_IRO_list | B12: E1-2 Climaterelated IRO list | C12: E1 | D12: E1-2 | E12: E1.MDR-P_01-06 | F12: =_xlfn.XLOOKUP(Table8[[#This Row],[Matched_Official_Datapoint_ID]], ESRS_MASTER!A:A, ESRS_MASTER!H:H, 0,0) -> Policies in place to manage its material impacts, risks and opportunities related to climate change mitigation and adaptation [see ESRS 2 MDR-P] | G12: Exact / near-exact DR-level semantic match | H12: High | I12: No | J12: DR cue detected: E1-2; Standard cue detected: E1; shared terms: climate, e1, impacts, opportunities, risks; score=0.84; runner-up gap=0.06 | K12: E1-2_01 | L12: Sustainability matters addressed by policy for climate change | M12: 0.78
A13: e1_E1-2/E1-9_Climaterelated_IRO_identificat | B13: E1-2/E1-9 Climaterelated IRO identificat | C13: E1 | D13: E1-2 | E13: E1.MDR-P_01-06 | F13: =_xlfn.XLOOKUP(Table8[[#This Row],[Matched_Official_Datapoint_ID]], ESRS_MASTER!A:A, ESRS_MASTER!H:H, 0,0) -> Policies in place to manage its material impacts, risks and opportunities related to climate change mitigation and adaptation [see ESRS 2 MDR-P] | G13: Exact / near-exact DR-level semantic match | H13: High | I13: No | J13: DR cue detected: E1-2; Standard cue detected: E1; shared terms: adaptation, climate, e1, impacts, mitigation, opportunities, risks; score=0.97; runner-up gap=0.16 | K13: E1-2_01 | L13: Sustainability matters addressed by policy for climate change | M13: 0.81
... A276: g1_G1-6_Payment_practices | B276: G1-6 Payment practices | C276: G1 | D276: G1-6 | E276: G1-6_05 | F276: =_xlfn.XLOOKUP(Table8[[#This Row],[Matched_Official_Datapoint_ID]], ESRS_MASTER!A:A, ESRS_MASTER!H:H, 0,0) -> Disclosure of contextual information regarding payment practices | G276: Exact / near-exact DR-level semantic match | H276: High | I276: No | J276: DR cue detected: G1-6; Standard cue detected: G1; shared terms: g1, payment, practices; score=0.96; runner-up gap=0.11 | K276: G1-6_03 | L276: Percentage of payments aligned with standard payment terms | M276: 0.85
A277: g1_G1/entity-specific_Animal_welfare_as_material_gov | B277: G1/entity-specific Animal welfare as material gov | F277: =_xlfn.XLOOKUP(Table8[[#This Row],[Matched_Official_Datapoint_ID]], ESRS_MASTER!A:A, ESRS_MASTER!H:H, 0,0) -> 0 | G277: No reliable official datapoint match | H277: Low | I277: Yes | J277: Standard cue detected: G1; shared terms: g1; score=0.22; runner-up gap=0.00 | K277: G1.MDR-A_13-14 | L277: Disclosures to be reported if the undertaking has not adopted actions | M277: 0.22
A278: s1_S1-1_Diversity_and_inclusion_approa | B278: S1-1 Diversity and inclusion approa | C278: S1 | D278: S1-1 | E278: S1-1_12 | F278: =_xlfn.XLOOKUP(Table8[[#This Row],[Matched_Official_Datapoint_ID]], ESRS_MASTER!A:A, ESRS_MASTER!H:H, 0,0) -> Disclosure of specific policy commitments related to inclusion and (or) positive action for people from groups at particular risk of vulnerability in own workforce | G278: Exact / near-exact DR-level semantic match | H278: High | I278: No | J278: DR cue detected: S1-1; Standard cue detected: S1; shared terms: inclusion, people, policy, s1, workforce; score=0.91; runner-up gap=0.00 | K278: S1-1_05 | L278: Disclosure of general approach in relation to engagement with people in its own workforce | M278: 0.90
A279: s1_S1-1_Health_and_safety_policy | B279: S1-1 Health and safety policy | C279: S1 | D279: S1-1 | E279: S1-1_18 | F279: =_xlfn.XLOOKUP(Table8[[#This Row],[Matched_Official_Datapoint_ID]], ESRS_MASTER!A:A, ESRS_MASTER!H:H, 0,0) -> Adjustments to the physical environment to ensure health and safety for workers, customers and other visitors with disabilities are in place | G279: Exact / near-exact DR-level semantic match | H279: High | I279: No | J279: DR cue detected: S1-1; Standard cue detected: S1; shared terms: environment, health, s1, safety; score=0.90; runner-up gap=0.02 | K279: S1-1_03 | L279: Description of relevant human rights policy commitments relevant to own workforce | M279: 0.88
A280: s1_S1-1_Human_Rights_Policy_and_Code_o | B280: S1-1 Human Rights Policy and Code o | C280: S1 | D280: S1-1 | E280: S1-1_03 | F280: =_xlfn.XLOOKUP(Table8[[#This Row],[Matched_Official_Datapoint_ID]], ESRS_MASTER!A:A, ESRS_MASTER!H:H, 0,0) -> Description of relevant human rights policy commitments relevant to own workforce | G280: Exact / near-exact DR-level semantic match | H280: High | I280: No | J280: DR cue detected: S1-1; Standard cue detected: S1; shared terms: human, policy, rights, s1; score=0.94; runner-up gap=0.07 | K280: S1-1_04 | L280: Disclosure of general approach in relation to respect for human rights including labour rights, of people in its own workforce | M280: 0.87
A281: s1_S1-1_Safety_policy | B281: S1-1 Safety policy | C281: S1 | D281: S1-1 | E281: S1-1_03 | F281: =_xlfn.XLOOKUP(Table8[[#This Row],[Matched_Official_Datapoint_ID]], ESRS_MASTER!A:A, ESRS_MASTER!H:H, 0,0) -> Description of relevant human rights policy commitments relevant to own workforce | G281: Exact / near-exact DR-level semantic match | H281: High | I281: No | J281: DR cue detected: S1-1; Standard cue detected: S1; shared terms: own, policy, s1, workforce; score=0.92; runner-up gap=0.04 | K281: S1-1_12 | L281: Disclosure of specific policy commitments related to inclusion and (or) positive action for people from groups at particular risk of vulnerability in own workforce | M281: 0.88
A282: s1_S1-1_Vision_Zero | B282: S1-1 Vision Zero | C282: S1 | D282: S1-1 | E282: S1-1_18 | F282: =_xlfn.XLOOKUP(Table8[[#This Row],[Matched_Official_Datapoint_ID]], ESRS_MASTER!A:A, ESRS_MASTER!H:H, 0,0) -> Adjustments to the physical environment to ensure health and safety for workers, customers and other visitors with disabilities are in place | G282: Exact / near-exact DR-level semantic match | H282: High | I282: No | J282: DR cue detected: S1-1; Standard cue detected: S1; shared terms: s1, safety; score=0.82; runner-up gap=0.03 | K282: S1-1_11 | L282: Grounds for discrimination are specifically covered in policy | M282: 0.79
A283: s1_S1-10/S1-13_GPTW_benchmark_target | B283: S1-10/S1-13 GPTW benchmark target | C283: S1 | D283: S1-10 | E283: S1-10_03 | F283: =_xlfn.XLOOKUP(Table8[[#This Row],[Matched_Official_Datapoint_ID]], ESRS_MASTER!A:A, ESRS_MASTER!H:H, 0,0) -> Percentage of employees paid below the applicable adequate wage benchmark | G283: Exact / near-exact DR-level semantic match | H283: High | I283: No | J283: DR cue detected: S1-10; Standard cue detected: S1; shared terms: 10, benchmark, s1; score=0.84; runner-up gap=0.00 | K283: S1-10_02 | L283: Countries where employees earn below the applicable adequate wage benchmark [table] | M283: 0.84
A284: s1_S1-13_Wellbeing,_health_and_safety_e | B284: S1-13 Wellbeing, health and safety e | C284: S1 | D284: S1-13 | E284: S1-13_05 | F284: =_xlfn.XLOOKUP(Table8[[#This Row],[Matched_Official_Datapoint_ID]], ESRS_MASTER!A:A, ESRS_MASTER!H:H, 0,0) -> Percentage of employees that participated in regular performance and career development reviews by employee category [table] | G284: Exact / near-exact DR-level semantic match | H284: High | I284: No | J284: DR cue detected: S1-13; Standard cue detected: S1; shared terms: 13, employee, s1; score=0.85; runner-up gap=0.00 | K284: S1-13_06 | L284: Average number of employees that participated in regular performance and career development reviews by employee category | M284: 0.85
A285: s1_S1-13/S1-4_Learning/growth_favourable_sco | B285: S1-13/S1-4 Learning/growth favourable sco | C285: S1 | D285: S1-13 | E285: S1-13_04 | F285: =_xlfn.XLOOKUP(Table8[[#This Row],[Matched_Official_Datapoint_ID]], ESRS_MASTER!A:A, ESRS_MASTER!H:H, 0,0) -> Average number of training hours per person for employees | G285: Exact / near-exact DR-level semantic match | H285: High | I285: No | J285: DR cue detected: S1-13; Standard cue detected: S1; shared terms: 13, employees, s1; score=0.90; runner-up gap=0.02 | K285: S1-13_02 | L285: Percentage of employees that participated in regular performance and career development reviews | M285: 0.87
A286: s1_S1-14_Absenteeism | B286: S1-14 Absenteeism | C286: S1 | D286: S1-14 | E286: S1-14_05 | F286: =_xlfn.XLOOKUP(Table8[[#This Row],[Matched_Official_Datapoint_ID]], ESRS_MASTER!A:A, ESRS_MASTER!H:H, 0,0) -> Rate of recordable work-related accidents for own workforce | G286: Exact / near-exact DR-level semantic match | H286: High | I286: No | J286: DR cue detected: S1-14; Standard cue detected: S1; shared terms: 14, rate, s1, workforce; score=1.04; runner-up gap=0.09 | K286: S1-14_04 | L286: Number of recordable work-related accidents for own workforce | M286: 0.94
A287: s1_S1-14_Accident_frequency_rate | B287: S1-14 Accident frequency rate | C287: S1 | D287: S1-14 | E287: S1-14_05 | F287: =_xlfn.XLOOKUP(Table8[[#This Row],[Matched_Official_Datapoint_ID]], ESRS_MASTER!A:A, ESRS_MASTER!H:H, 0,0) -> Rate of recordable work-related accidents for own workforce | G287: Exact / near-exact DR-level semantic match | H287: High | I287: No | J287: DR cue detected: S1-14; Standard cue detected: S1; shared terms: 14, rate, s1; score=0.93; runner-up gap=0.07 | K287: S1-14_04 | L287: Number of recordable work-related accidents for own workforce | M287: 0.85
A288: s1_S1-14_Accident_severity_rate | B288: S1-14 Accident severity rate | C288: S1 | D288: S1-14 | E288: S1-14_05 | F288: =_xlfn.XLOOKUP(Table8[[#This Row],[Matched_Official_Datapoint_ID]], ESRS_MASTER!A:A, ESRS_MASTER!H:H, 0,0) -> Rate of recordable work-related accidents for own workforce | G288: Exact / near-exact DR-level semantic match | H288: High | I288: No | J288: DR cue detected: S1-14; Standard cue detected: S1; shared terms: 14, rate, s1; score=0.94; runner-up gap=0.08 | K288: S1-14_04 | L288: Number of recordable work-related accidents for own workforce | M288: 0.86
A289: s1_S1-14_Fatalities | B289: S1-14 Fatalities | C289: S1 | D289: S1-14 | E289: S1-14_02 | F289: =_xlfn.XLOOKUP(Table8[[#This Row],[Matched_Official_Datapoint_ID]], ESRS_MASTER!A:A, ESRS_MASTER!H:H, 0,0) -> Number of fatalities in own workforce as result of work-related injuries and work-related ill health | G289: Exact / near-exact DR-level semantic match | H289: High | I289: No | J289: DR cue detected: S1-14; Standard cue detected: S1; shared terms: 14, fatalities, health, ill, injuries, number, s1, work; score=1.26; runner-up gap=0.03 | K289: S1-14_07 | L289: Number of days lost to work-related injuries and fatalities from work-related accidents, work-related ill health and fatalities from ill health related to employees | M289: 1.23
... A379: s4_S4-5_Withdrawals_and_recalls | B379: S4-5 Withdrawals and recalls | C379: S4 | D379: S4-5 | E379: S4-5_06 | F379: =_xlfn.XLOOKUP(Table8[[#This Row],[Matched_Official_Datapoint_ID]], ESRS_MASTER!A:A, ESRS_MASTER!H:H, 0,0) -> Disclosure of references to standards or commitments on which target is based | G379: Exact / near-exact DR-level semantic match | H379: High | I379: No | J379: DR cue detected: S4-5; Standard cue detected: S4; shared terms: s4; score=0.79; runner-up gap=0.01 | K379: S4-5_01 | L379: Disclosure of whether and how consumers and end-users were engaged directly in setting targets | M379: 0.79

Sheet MAPPING
A1: Company | B1: Integrated/ Sustainability | C1: Report_Year | D1: ESRS/ GRI | E1: Updated Version Available? | F1: Contact_Person | G1: Source
A2: Mowi | B2: Integrated | C2: 2025 | D2: ESRS | G2: https://mowi.com/wp-content/uploads/2025/05/Mowi-Annual-Report-2025.pdf
A3: Bolton | B3: Sustainability | C3: 2024 | D3: ESRS | E3: 2025 | F3: Laura Pisani
A4: Espersen | B4: Sustainability | C4: 2024 | D4: ESRS | E4: 2025 | F4: Jennie Montell
A5: Nomad | B5: Sustainability | C5: 2024 | D5: GRI | F5: Oliver Spring
A6: Profand | B6: Sustainability | C6: 2024 | D6: GRI
A7: Thai Unioin | B7: Sustainability | C7: 2024 | D7: GRI (accordance) | F7: Tony Lazazzara | G7: https://www.thaiunion.com/uploads/sd-report-2024-en.pdf
A13: side-quest
A14: analyse 2024 vs 2025
A15: what does european vs non-european do
A688: MAP-0687
A689: MAP-0688
A690: MAP-0689
A691: MAP-0690
A692: MAP-0691
A693: MAP-0692
A694: MAP-0693
A695: MAP-0694
A696: MAP-0695
... A1501: MAP-1500

Sheet Mowi_Mapping
A1: Company | B1: Topic | C1: DR / Reference | D1: Datapoint Name | E1: Page Reference | F1: DR Type
A2: Mowi | B2: E1 | C2: E1-1 | D2: Transition plan for climate change mitigation | E2: 96 | F2: Topical DR
A3: Mowi | B3: E1 | C3: E1 IRO-1 | D3: Climate change related risks and opportunities | E3: 99 | F3: Cross-cutting (IRO)
A4: Mowi | B4: E1 | C4: E1-3 | D4: Actions and resources | E4: 101 | F4: Topical DR
A5: Mowi | B5: E1 | C5: E1-4 | D5: Targets and metrics | E5: 102 | F5: Topical DR
A6: Mowi | B6: E1 | C6: E1-5 | D6: Energy consumption and mix | E6: 103 | F6: Topical DR
A7: Mowi | B7: E1 | C7: E1-6 | D7: Gross scopes 1, 2, 3 and total GHG emissions | E7: 104 | F7: Topical DR
A8: Mowi | B8: E3 | C8: E3 SBM-3 | D8: Material impacts, risks, and opportunities related to water and marine resources | E8: 110 | F8: Cross-cutting (SBM)
A9: Mowi | B9: E3 | C9: E3-1 | D9: Management of impacts, risks and opportunities | E9: 112 | F9: Topical DR
A10: Mowi | B10: E3 | C10: E3-2 | D10: Actions and resources | E10: 113 | F10: Topical DR
A11: Mowi | B11: E3 | C11: E3-3 | D11: Targets and metrics | E11: 115 | F11: Topical DR
A12: Mowi | B12: E3 | C12: E3-4 | D12: Water consumption and marine resource performance | E12: 115 | F12: Topical DR
A13: Mowi | B13: E4 | C13: E4-1 | D13: Consideration of biodiversity and ecosystems in strategy and business model | E13: 120 | F13: Topical DR
... A50: Mowi | B50: G1 | C50: G1-4 | D50: Confirmed incidents of corruption or bribery | E50: 164 | F50: Topical DR

Sheet MOWI_Mapping_Datapoints
A1: Company | B1: Topic | C1: DR | D1: Datapoint name | E1: Page reference | F1: Comments | G1: Relevance to seafood processing | H1: Business activity flag | I1: Notes on ambiguity
A2: Mowi | B2: E1 | C2: E1-1 | D2: Transition plan to reach climate neutrality by 2050 paragraph 14 | E2: 96
A3: Mowi | B3: E1 | C3: E1-1 | D3: Undertakings excluded from Paris-aligned Benchmarks paragraph 16 (g) | E3: 96 | F3: Delegated Regulation (EU) 2020/1818 Article12.1 (d) to (g) and Article 12.2
A4: Mowi | B4: E1 | C4: E1-4 | D4: GHG emission reduction targets paragraph 34 | E4: 102 | F4: Indicator number 4 Table #2 of Annex 1
A5: Mowi | B5: E1 | C5: E1-5 | D5: Energy consumption from fossil sources disaggregated by sources (only high climate impact sectors) paragraph 38 | E5: 103 | F5: Indicator number 5 Table #1 and Indicator n.5 Table #2 of Annex 1
A6: Mowi | B6: E1 | C6: E1-5 | D6: Energy consumption and mix paragraph 37 | E6: 103 | F6: Indicator number 5 Table #1 of Annex 1
A7: Mowi | B7: E1 | C7: E1-5 | D7: Energy intensity associated with activities in high climate impact sectors paragraphs 40 to 43 | E7: 103 | F7: Indicator number 6 Table #1 of Annex 1
A8: Mowi | B8: E1 | C8: E1-6 | D8: Gross Scope 1 2 3 and Total GHG emissions paragraph 44 | E8: 104 | F8: Indicators number 1 and 2 Table #1 of Annex 1
A9: Mowi | B9: E1 | C9: E1-6 | D9: Gross GHG emissions intensity paragraphs 53 to 55 | E9: 104 | F9: Indicators number 3 Table #1 of Annex 1
A10: Mowi | B10: E2 | C10: E2-4 | D10: Amount of each pollutant listed in Annex II of the E-PRTR Regulation emitted to air water and soil paragraph 28 | F10: Indicator number 8 Table #1 of Annex 1 Indicator number 2 Table #2 of Annex 1 Indicator number 1 Table #2 of Annex 1
A11: Mowi | B11: E3 | C11: E3-1 | D11: Water and marine resources paragraph 9 | E11: 112 | F11: Indicator number 7 Table #2 of Annex 1
A12: Mowi | B12: E3 | C12: E3-1 | D12: Dedicated policy paragraph 13 | E12: 113 | F12: Indicator number 8 Table #2 of Annex 1
A13: Mowi | B13: E3 | C13: E3-1 | D13: Sustainable oceans and seas paragraph 14 | E13: 113 | F13: Indicator number 12 Table #2 of Annex 1
A14: Mowi | B14: E3 | C14: E3-4 | D14: Total water recycled and reused paragraph 28 (c) | E14: 115 | F14: Indicator number 62 Table #2 of Annex 1
A15: Mowi | B15: E3 | C15: E3-4 | D15: Total water consumption in m3 per net revenue on own operations paragraph 29 | E15: 116 | F15: Indicator number 61 Table #2 of Annex 1
A16: Mowi | B16: E2 | C16: S2-SBM-3 | D16: E4 paragraph 16 (a) | E16: 122 | F16: Indicator number 7 Table #1 of Annex 1
A17: Mowi | B17: E2 | C17: S2-SBM-3 | D17: E4 paragraph 16 (b) | E17: 122 | F17: Indicator number 10 Table #2 of Annex 1
A18: Mowi | B18: E2 | C18: S2-SBM-3 | D18: E4 paragraph 16 (c) | E18: 123 | F18: Indicator number 14 Table #2 of Annex 1
A19: Mowi | B19: E4 | C19: E4-2 | D19: Sustainable land agriculture practices or policies paragraph 24 (d) | E19: 126 | F19: Indicator number 11 Table #2 of Annex 1
A20: Mowi | B20: E4 | C20: E4-2 | D20: Sustainable oceans seas practices or policies paragraph 24 (g) | E20: 127 | F20: Indicator number 12 Table #2 of Annex 1
A21: Mowi | B21: E4 | C21: E4-2 | D21: Policies to address deforestation paragraph 24 (d) | E21: 127 | F21: Indicator number 15 Table #1 of Annex 1
A22: Mowi | B22: S2 | C22: S2-SBM-3 | D22: S1 Risk of incidents of forced labour paragraph 14 (f) | E22: 149 | F22: Indicator number 13 Table #3 of Annex 1
A23: Mowi | B23: S2 | C23: S2-SBM-3 | D23: S1 Risk of incidents of child labour paragraph 14 (g) | E23: 149 | F23: Indicator number 12 Table #3 of Annex 1
A24: Mowi | B24: S1 | C24: S1-1 | D24: Human rights policy commitments paragraph 20 | E24: 141-142 | F24: Indicator number 9 Table #3 and Indicator number 11 Table #1 of Annex 1
A25: Mowi | B25: S1 | C25: S1-1 | D25: Due diligence policies on issues addressed by fundamental ILO Conventions paragraph 21 | E25: 141-142
A26: Mowi | B26: S1 | C26: S1-1 | D26: Processes and measures for preventing trafficking in human beings paragraph 22 | E26: 141-142 | F26: Indicator number 11 Table #3 of Annex 1
A27: Mowi | B27: S1 | C27: S1-1 | D27: Workplace accident prevention policy or management system paragraph 23 | E27: 141 | F27: Indicator number 1 Table #3 of Annex 1
A28: Mowi | B28: S1 | C28: S1-3 | D28: Grievance complaints handling mechanisms paragraph 32 (c) | E28: 142 | F28: Indicator number 5 Table #3 of Annex 1
A29: Mowi | B29: S1 | C29: S1-14 | D29: Number of fatalities and number rate of work related accidents paragraph 88 (b) and (c) | E29: 145 | F29: Indicator number 2 Table #3 of Annex 1
A30: Mowi | B30: S1 | C30: S1-14 | D30: Number of days lost to injuries accidents fatalities or illness paragraph 88 (e) | E30: 145 | F30: Indicator number 3 Table #3 of Annex 1
A31: Mowi | B31: S1 | C31: S1-16 | D31: Unadjusted gender pay gap paragraph 97 (a) | E31: 147 | F31: Indicator number 12 Table #1 of Annex 1
A32: Mowi | B32: S1 | C32: S1-16 | D32: Excessive CEO pay ratio paragraph 97 (b) | E32: 147 | F32: Indicator number 8 Table #3 of Annex 1
A33: Mowi | B33: S1 | C33: S1-17 | D33: Incidents of discrimination paragraph 103 (a) | E33: 150 | F33: Indicator number 7 Table #3 of Annex 1
A34: Mowi | B34: S1 | C34: S1-17 | D34: Non-respect of UNGPs Business and Human Rights and OECD Guidelines paragraph 104 (a) | E34: 150 | F34: Indicator number 10 Table #1 and Indicator n.14 Table #3 of Annex 1
A35: Mowi | B35: S2 | C35: S2-SBM-3 | D35: S2 Significant risk of child labour or forced labour in value chain paragraph 11 (b) | E35: 156 | F35: Indicators number 12 and 13 Table #3 of Annex 1
A36: Mowi | B36: S2 | C36: S2-1 | D36: Human rights policy commitments paragraph 17 | E36: 157 | F36: Indicator number 9 Table #3 and Indicator n.10 Table #1 of Annex 1
A37: Mowi | B37: S2 | C37: S2-1 | D37: Policies related to value chain workers paragraph 18 | E37: 157 | F37: Indicator number 11 and 4 Table #3 of Annex 1
A38: Mowi | B38: S2 | C38: S2-1 | D38: Non-respect of UNGPs Business and Human Rights principles paragraph 19 | E38: 157 | F38: Indicator number 10 Table #1 of Annex 1
A39: Mowi | B39: S2 | C39: S2-1 | D39: Due diligence policies on issues addressed by fundamental ILO Conventions paragraph 19 | E39: 157
A40: Mowi | B40: S2 | C40: S2-4 | D40: Human rights issues and incidents connected to upstream and downstream value chain paragraph 36 | E40: 160 | F40: Indicator number 14 Table #3 of Annex 1
A41: Mowi | B41: G1 | C41: G1-1 | D41: United Nations Convention against Corruption paragraph 10 (b) | E41: 162 | F41: Indicator number 15 Table #3 of Annex 1
A42: Mowi | B42: G1 | C42: G1-1 | D42: Protection of whistle-blowers paragraph 10 (d) | E42: 162 | F42: Indicator number 6 Table #3 of Annex 1
A43: Mowi | B43: G1 | C43: G1-4 | D43: Fines for violation of anti-corruption and anti-bribery laws paragraph 24 (a) | E43: 162 | F43: Indicator number 17 Table #3 of Annex 1
A44: Mowi | B44: G1 | C44: G1-4 | D44: Standards of anti-corruption and anti-bribery paragraph 24 (b) | E44: 162 | F44: Indicator number 16 Table #3 of Annex 1

Sheet Espersen_Mapping
A1: Company | B1: Topic | C1: DR | D1: Datapoint name | E1: Page reference | F1: Comments | G1: Page reference | H1: Mapping type | I1: Coverage status | J1: Relevance to seafood processing | K1: Business activity flag | L1: Notes on ambiguity
A2: Espersen | B2: E1 | C2: E1-1 | D2: Transition plan for climate change mitigation | E2: - | F2: Current data gaps/alignment in progress
A3: Espersen | B3: E1 | C3: E1-2 | D3: Policies related to climate change mitigation and adaptation | E3: 24
A4: Espersen | B4: E1 | C4: E1-3 | D4: Actions and resources in relation to climate change policies | E4: 27
A5: Espersen | B5: E1 | C5: E1-4 | D5: Targets related to climate change mitigation and adaptation | E5: 26; 87
A6: Espersen | B6: E1 | C6: E1-5 | D6: Energy consumption and mix | E6: 28–29; 89
A7: Espersen | B7: E1 | C7: E1-6 | D7: Gross scopes 1, 2, 3 and total GHG emissions | E7: 25; 86
A8: Espersen | B8: E1 | C8: E1-9 | D8: Anticipated financial effects from material physical and transition risks and potential climate-related opportunities | E8: - | F8: Phase in disclosure
A9: Espersen | B9: E3 | C9: E3-1 | D9: Policies related to water and marine resources | E9: 30; 32
A10: Espersen | B10: E3 | C10: E3-2 | D10: Actions and resources related to water and marine resources | E10: 30; 33
A11: Espersen | B11: E3 | C11: E3-3 | D11: Targets related to water and marine resources | E11: 32
A12: Espersen | B12: E3 | C12: E3-4 | D12: Water consumption | E12: 90
A13: Espersen | B13: E3 | C13: E3-5 | D13: Anticipated financial effects from water and marine resources-related impacts risks and opportunities | E13: - | F13: Phase in disclosure
A14: Espersen | B14: E4 | C14: E4-1 | D14: Transition plan on biodiversity and ecosystems | E14: 34; 36
A15: Espersen | B15: E4 | C15: E4-2 | D15: Policies related to biodiversity and ecosystems | E15: 34; 36
A16: Espersen | B16: E4 | C16: E4-3 | D16: Actions and resources related to biodiversity and ecosystems | E16: 35–36
A17: Espersen | B17: E4 | C17: E4-4 | D17: Targets related to biodiversity and ecosystems | E17: - | F17: Current data gaps/alignment in progress
A18: Espersen | B18: E4 | C18: E4-5 | D18: Impact metrics related to biodiversity and ecosystems change | E18: - | F18: Current data gaps/alignment in progress
A19: Espersen | B19: E4 | C19: E4-6 | D19: Anticipated financial effects from biodiversity and ecosystems-related risks and opportunities | E19: - | F19: Phase in disclosure
A20: Espersen | B20: E5 | C20: E5-1 | D20: Policies related to resource use and circular economy | E20: 39; 41
A21: Espersen | B21: E5 | C21: E5-2 | D21: Actions and resources related to resource use and circular economy | E21: 40; 44
A22: Espersen | B22: E5 | C22: E5-3 | D22: Targets related to resource use and circular economy | E22: 39–42
A23: Espersen | B23: E5 | C23: E5-4 | D23: Resource inflows | E23: 37–38
A24: Espersen | B24: E5 | C24: E5-5 | D24: Resource outflows | E24: 41–43
A25: Espersen | B25: E5 | C25: E5-6 | D25: Anticipated financial effects from material resource use and circular economy-related risks and opportunities | E25: - | F25: Phase in disclosure
A26: Espersen | B26: S1 | C26: S1-1 | D26: Policies related to own workforce | E26: 48; 50 | F26: Covering only H&S and diversity related topics
A27: Espersen | B27: S1 | C27: S1-2 | D27: Processes for engaging with own workers and workers’ representatives about impacts | E27: - | F27: Current data gaps/alignment in progress
A28: Espersen | B28: S1 | C28: S1-3 | D28: Processes to remediate negative impacts and channels for own workers to raise concerns | E28: - | F28: Current data gaps/alignment in progress
A29: Espersen | B29: S1 | C29: S1-4 | D29: Taking action on material impacts on own workforce and approaches to mitigating material risks and pursuing material opportunities and effectiveness of those actions | E29: 46–47
A30: Espersen | B30: S1 | C30: S1-5 | D30: Targets related to managing material negative impacts advancing positive impacts and managing material risks and opportunities | E30: - | F30: Current data gaps/alignment in progress
A31: Espersen | B31: S1 | C31: S1-6 | D31: Characteristics of the undertaking’s employees | E31: 91
A32: Espersen | B32: S1 | C32: S1-7 | D32: Characteristics of non-employee workers in the undertaking’s own workforce | E32: - | F32: Phase in disclosure
A33: Espersen | B33: S1 | C33: S1-8 | D33: Collective bargaining coverage and social dialogue | E33: - | F33: Current data gaps/alignment in progress
A34: Espersen | B34: S1 | C34: S1-9 | D34: Diversity metrics | E34: 48–49; 91–92
A35: Espersen | B35: S1 | C35: S1-10 | D35: Adequate wages | E35: - | F35: Current data gaps/alignment in progress
A36: Espersen | B36: S1 | C36: S1-11 | D36: Social protection | E36: - | F36: Phase in disclosure
A37: Espersen | B37: S1 | C37: S1-12 | D37: Persons with disabilities | E37: - | F37: Non-material sub-topic
A38: Espersen | B38: S1 | C38: S1-13 | D38: Training and skills development metrics | E38: - | F38: Phase in disclosure
A39: Espersen | B39: S1 | C39: S1-14 | D39: Health and safety metrics | E39: 51; 93
A40: Espersen | B40: S1 | C40: S1-16 | D40: Compensation metrics (pay gap and total compensation) | E40: - | F40: Current data gaps/alignment in progress
A41: Espersen | B41: S1 | C41: S1-17 | D41: Incidents complaints and severe human rights impacts | E41: - | F41: Current data gaps/alignment in progress
A42: Espersen | B42: S2 | C42: S2-1 | D42: Policies related to value chain workers | E42: 54
A43: Espersen | B43: S2 | C43: S2-2 | D43: Processes for engaging with value chain workers about impacts | E43: - | F43: Current data gaps/reporting alignment in progress
A44: Espersen | B44: S2 | C44: S2-3 | D44: Processes to remediate negative impacts and channels for value chain workers to raise concerns | E44: 55
A45: Espersen | B45: S2 | C45: S2-4 | D45: Taking action on material impacts on value chain workers and approaches to managing material risks and pursuing material opportunities and effectiveness of those actions | E45: 53–54
A46: Espersen | B46: S2 | C46: S2-5 | D46: Targets related to managing material negative impacts advancing positive impacts and managing material risks and opportunities | E46: 54
A47: Espersen | B47: S4 | C47: S4-1 | D47: Policies related to consumers and end-users | E47: 57
A48: Espersen | B48: S4 | C48: S4-2 | D48: Processes for engaging with consumers and end-users about impacts | E48: 60
A49: Espersen | B49: S4 | C49: S4-3 | D49: Processes to remediate negative impacts and channels for consumers and end-users to raise concerns | E49: 61
A50: Espersen | B50: S4 | C50: S4-4 | D50: Taking action on material impacts on consumers and end-users and approaches to managing material risks and pursuing material opportunities and effectiveness of those actions | E50: 58–59
A51: Espersen | B51: S4 | C51: S4-5 | D51: Targets related to managing material negative impacts advancing positive impacts and managing material risks and opportunities | E51: 59
A52: Espersen | B52: G1 | C52: G1-1 | D52: Corporate culture and business conduct policies and corporate culture | E52: 63-64
A53: Espersen | B53: G1 | C53: G1-2 | D53: Management of relationships with suppliers | E53: 67-70
A54: Espersen | B54: G1 | C54: G1-3 | D54: Prevention and detection of corruption and bribery | E54: 64-65
A55: Espersen | B55: G1 | C55: G1-4 | D55: Confirmed incidents of corruption or bribery | E55: 65
A56: Espersen | B56: G1 | C56: G1-5 | D56: Political influence and lobbying activities | E56: 66
A57: Espersen | B57: G1 | C57: G1-6 | D57: Payment practices

Sheet Bolton_Mapping
A1: Company | B1: Topic | C1: DR | D1: Datapoint name | E1: Page reference | F1: Comments | G1: Coverage status | H1: Relevance to seafood processing | I1: Business activity flag | J1: Notes on ambiguity
A2: Bolton | B2: E1 | C2: E1-1 | D2: Transition plan for climate change mitigation | E2: 60–68
A3: Bolton | B3: E1 | C3: E1-2 | D3: Policies related to climate change mitigation and adaptation | E3: 59
A4: Bolton | B4: E1 | C4: E1-3 | D4: Actions and resources in relation to climate change policies | E4: 60–68
A5: Bolton | B5: E1 | C5: E1-4 | D5: Targets related to climate change mitigation and adaptation | E5: 60
A6: Bolton | B6: E1 | C6: E1-5 | D6: Energy consumption and mix | E6: 77–80
A7: Bolton | B7: E1 | C7: E1-6 | D7: Gross Scopes 1,2, 3 and Total GHG emissions
A8: Bolton | B8: E3 | C8: E3-1 | D8: Policies related to water and marine resources | E8: 112; 120–121
A9: Bolton | B9: E3 | C9: E3-2 | D9: Actions and resources related to water and marine resources | E9: 121–131
A10: Bolton | B10: E3 | C10: E3-3 | D10: Targets related to water and marine resources | E10: 113; 132
A11: Bolton | B11: E3 | C11: E3-4 | D11: Water consumption | E11: 114–116
A12: Bolton | B12: E5 | C12: E5-1 | D12: Policies related to resource use and circular economy | E12: 84–85
A13: Bolton | B13: E5 | C13: E5-2 | D13: Actions and resources related to resource use and circular economy | E13: 86–88
A14: Bolton | B14: E5 | C14: E5-3 | D14: Targets related to resource use and circular economy | E14: 92
A15: Bolton | B15: E5 | C15: E5-4 | D15: Resource inflows | E15: 94–98
A16: Bolton | B16: E5 | C16: E5-5 | D16: Resource outflows | E16: 97; 98–101
A17: Bolton | B17: S1 | C17: S1-1 | D17: Policies related to own workforce | E17: 143
A18: Bolton | B18: S1 | C18: S1-2 | D18: Processes for engaging with own workers and workers’ representatives about impacts | E18: 144–145
A19: Bolton | B19: S1 | C19: S1-3 | D19: Processes to remediate negative impacts and channels for own workers to raise concerns | E19: 145
A20: Bolton | B20: S1 | C20: S1-4 | D20: Taking action on material impacts on own workforce, and approaches to mitigating material risks and pursuing material opportunities related to own workforce, and effectiveness of those actions | E20: 146–147
A21: Bolton | B21: S1 | C21: S1-5 | D21: Targets related to managing material negative impacts, advancing positive impacts, and managing material risks and opportunities | E21: 148–149
A22: Bolton | B22: S1 | C22: S1-6 | D22: Characteristics of the undertaking’s employees | E22: 149–151
A23: Bolton | B23: S1 | C23: S1-7 | D23: Characteristics of non-employee workers in the undertaking’s own workforce | E23: 152
A24: Bolton | B24: S1 | C24: S1-8 | D24: Collective bargaining coverage and social dialogue | E24: 152–153
A25: Bolton | B25: S1 | C25: S1-9 | D25: Diversity metrics | E25: 154
A26: Bolton | B26: S1 | C26: S1-10 | D26: Adequate wages | E26: 155
A27: Bolton | B27: S1 | C27: S1-11 | D27: Social protection | E27: 155–156
A28: Bolton | B28: S1 | C28: S1-12 | D28: Persons with disabilities | E28: 157
A29: Bolton | B29: S1 | C29: S1-13 | D29: Training and skills development metrics | E29: 157–158
A30: Bolton | B30: S1 | C30: S1-14 | D30: Health and safety metrics | E30: 158–159
A31: Bolton | B31: S1 | C31: S1-15 | D31: Work-life balance metrics | E31: 159
A32: Bolton | B32: S1 | C32: S1-17 | D32: Incidents, complaints and severe human rights impacts | E32: 159
A33: Bolton | B33: S2 | C33: S2-1 | D33: Policies related to value chain workers | E33: 163–164
A34: Bolton | B34: S2 | C34: S2-2 | D34: Processes for engaging with value chain workers about impacts | E34: 165–166
A35: Bolton | B35: S2 | C35: S2-3 | D35: Processes to remediate negative impacts and channels for value chain workers to raise concerns | E35: 164
A36: Bolton | B36: S3 | C36: S3-1 | D36: Policies related to affected communities | E36: 163–164
A37: Bolton | B37: S3 | C37: S3-2 | D37: Processes for engaging with affected communities about impacts | E37: 156; 165–167
A38: Bolton | B38: S3 | C38: S3-3 | D38: Processes to remediate negative impacts and channels for affected communities to raise concerns | E38: 164
A39: Bolton | B39: S3 | C39: S3-4 | D39: Taking action on material impacts on affected communities, and approaches to managing material risks and pursuing material opportunities related to affected communities, and effectiveness of those actions | E39: 156; 165–167
A40: Bolton | B40: S3 | C40: S3-5 | D40: Targets related to managing material negative impacts, advancing positive impacts, and managing material risks and opportunities | E40: 148
A41: Bolton | B41: S4 | C41: S4-1 | D41: Policies related to consumers and end-users | E41: 163–164
A42: Bolton | B42: S4 | C42: S4-3 | D42: Processes to remediate negative impacts and channels for consumers to raise concerns | E42: 170–171
A43: Bolton | B43: S4 | C43: S3-4 | D43: Taking action on material impacts on consumers, and approaches to managing material risks and pursuing material opportunities related to affected consumers, and effectiveness of those actions | E43: 170–171
A44: Bolton | B44: G1 | C44: G1-1 | D44: Business conduct policies and corporate culture | E44: 180–184
A45: Bolton | B45: G1 | C45: G1-2 | D45: Management of relationships with suppliers | E45: 185
A46: Bolton | B46: G1 | C46: G1-3 | D46: Prevention and detection of corruption and bribery | E46: 185
A47: Bolton | B47: G1 | C47: G1-5 | D47: Political influence and lobbying activities | E47: 186

Sheet Profand_Mapping
A1: Company | B1: Topic | C1: DR | D1: Datapoint name | E1: Page reference | F1: Comments
A2: Profand | B2: =LEFT(C2, FIND("-", C2) - 1) -> S1 | C2: =[1]Profand_Topical_Mapping!H2 -> S1-6 | D2: =[1]Profand_Topical_Mapping!D2 -> Employees | E2: =[1]Profand_Topical_Mapping!E2 -> Annex 1
A3: Profand | B3: =LEFT(C3, FIND("-", C3) - 1) -> S1 | C3: =[1]Profand_Topical_Mapping!H3 -> S1-7 | D3: =[1]Profand_Topical_Mapping!D3 -> Non-employee workers | E3: =[1]Profand_Topical_Mapping!E3 -> Work continues to report on this indicator in future versions of the ESG Report
A4: Profand | B4: =LEFT(C4, FIND("-", C4) - 1) -> G1 | C4: =[1]Profand_Topical_Mapping!H4 -> G1-3 | D4: =[1]Profand_Topical_Mapping!D4 -> Delegation of responsibility for impact management | E4: =[1]Profand_Topical_Mapping!E4 -> 4.4. Compliance, good corporate governance and fiscal transparency
A5: Profand | B5: =LEFT(C5, FIND("-", C5) - 1) -> S1 | C5: =[1]Profand_Topical_Mapping!H5 -> S1-16 | D5: =[1]Profand_Topical_Mapping!D5 -> Total annual compensation ratio | E5: =[1]Profand_Topical_Mapping!E5 -> Annex 1
A6: Profand | B6: =LEFT(C6, FIND("-", C6) - 1) -> S1 | C6: =[1]Profand_Topical_Mapping!H6 -> S1-1 | D6: =[1]Profand_Topical_Mapping!D6 -> Commitments and policies | E6: =[1]Profand_Topical_Mapping!E6 -> 2.2. Quality and the customer at the heart of our activity / 4.2. Protection and respect for human and labor rights / 4.4. Compliance, good corporate governance and fiscal transparency
A7: Profand | B7: =LEFT(C7, FIND("-", C7) - 1) -> S2 | C7: =[1]Profand_Topical_Mapping!H7 -> S2-1 | D7: =[1]Profand_Topical_Mapping!D7 -> Commitments and policies | E7: =[1]Profand_Topical_Mapping!E7 -> 2.2. Quality and the customer at the heart of our activity / 4.2. Protection and respect for human and labor rights / 4.4. Compliance, good corporate governance and fiscal transparency
A8: Profand | B8: =LEFT(C8, FIND("-", C8) - 1) -> G1 | C8: =[1]Profand_Topical_Mapping!H8 -> G1-1 | D8: =[1]Profand_Topical_Mapping!D8 -> Commitments and policies | E8: =[1]Profand_Topical_Mapping!E8 -> 2.2. Quality and the customer at the heart of our activity / 4.2. Protection and respect for human and labor rights / 4.4. Compliance, good corporate governance and fiscal transparency
A9: Profand | B9: =LEFT(C9, FIND("-", C9) - 1) -> G1 | C9: =[1]Profand_Topical_Mapping!H9 -> G1-1 | D9: =[1]Profand_Topical_Mapping!D9 -> Incorporating commitments and policies | E9: =[1]Profand_Topical_Mapping!E9 -> 2.2. Quality and the customer at the heart of our activity / 4.2. Protection and respect for human and labor rights
A10: Profand | B10: =LEFT(C10, FIND("-", C10) - 1) -> S1 | C10: =[1]Profand_Topical_Mapping!H10 -> S1-1 | D10: =[1]Profand_Topical_Mapping!D10 -> Processes to remedy negative impacts | E10: =[1]Profand_Topical_Mapping!E10 -> 4.4. Compliance, good corporate governance and fiscal transparency
A11: Profand | B11: =LEFT(C11, FIND("-", C11) - 1) -> S1 | C11: =[1]Profand_Topical_Mapping!H11 -> S1-3 | D11: =[1]Profand_Topical_Mapping!D11 -> Processes to remedy negative impacts | E11: =[1]Profand_Topical_Mapping!E11 -> 4.4. Compliance, good corporate governance and fiscal transparency
A12: Profand | B12: =LEFT(C12, FIND("-", C12) - 1) -> S2 | C12: =[1]Profand_Topical_Mapping!H12 -> S2-1 | D12: =[1]Profand_Topical_Mapping!D12 -> Processes to remedy negative impacts | E12: =[1]Profand_Topical_Mapping!E12 -> 4.4. Compliance, good corporate governance and fiscal transparency
A13: Profand | B13: =LEFT(C13, FIND("-", C13) - 1) -> S2 | C13: =[1]Profand_Topical_Mapping!H13 -> S2-3 | D13: =[1]Profand_Topical_Mapping!D13 -> Processes to remedy negative impacts | E13: =[1]Profand_Topical_Mapping!E13 -> 4.4. Compliance, good corporate governance and fiscal transparency
... A77: Profand | B77: =LEFT(C77, FIND("-", C77) - 1) -> S4 | C77: =[1]Profand_Topical_Mapping!H77 -> S4-4 | D77: =[1]Profand_Topical_Mapping!D77 -> Substantiated complaints regarding breaches of customer privacy and loss of customer data | E77: =[1]Profand_Topical_Mapping!E77 -> 0

Sheet Nomad_Mapping
A1: Company | B1: Topic | C1: DR | D1: Datapoint name | E1: Page reference | F1: Comments
A2: Nomad | B2: =LEFT(C2, FIND("-", C2) - 1) -> S1 | C2: =[2]Nomad_Topical_Mapping!H2 -> S1-6 | D2: =[2]Nomad_Topical_Mapping!D2 -> Total number of employees | E2: =[2]Nomad_Topical_Mapping!E2 -> Data tables
A3: Nomad | B3: =LEFT(C3, FIND("-", C3) - 1) -> S1 | C3: =[2]Nomad_Topical_Mapping!H3 -> S1-6 | D3: =[2]Nomad_Topical_Mapping!D3 -> Employee breakdown by gender and region | E3: =[2]Nomad_Topical_Mapping!E3 -> Data tables
A4: Nomad | B4: =LEFT(C4, FIND("-", C4) - 1) -> G1 | C4: =[2]Nomad_Topical_Mapping!H4 -> G1-3 | D4: =[2]Nomad_Topical_Mapping!D4 -> Delegation of responsibility | E4: =[2]Nomad_Topical_Mapping!E4 -> Sustainability governance
A5: Nomad | B5: =LEFT(C5, FIND("-", C5) - 1) -> S1 | C5: =[2]Nomad_Topical_Mapping!H5 -> S1-1 | D5: =[2]Nomad_Topical_Mapping!D5 -> Policy commitments for responsible business conduct | E5: =[2]Nomad_Topical_Mapping!E5 -> Sustainability governance / Code of Business Principles / Supplier Code of Conduct
A6: Nomad | B6: =LEFT(C6, FIND("-", C6) - 1) -> S2 | C6: =[2]Nomad_Topical_Mapping!H6 -> S2-1 | D6: =[2]Nomad_Topical_Mapping!D6 -> Policy commitments for responsible business conduct | E6: =[2]Nomad_Topical_Mapping!E6 -> Sustainability governance / Code of Business Principles / Supplier Code of Conduct
A7: Nomad | B7: =LEFT(C7, FIND("-", C7) - 1) -> G1 | C7: =[2]Nomad_Topical_Mapping!H7 -> G1-1 | D7: =[2]Nomad_Topical_Mapping!D7 -> Policy commitments for responsible business conduct | E7: =[2]Nomad_Topical_Mapping!E7 -> Sustainability governance / Code of Business Principles / Supplier Code of Conduct
A8: Nomad | B8: =LEFT(C8, FIND("-", C8) - 1) -> G1 | C8: =[2]Nomad_Topical_Mapping!H8 -> G1-1 | D8: =[2]Nomad_Topical_Mapping!D8 -> Embedding policy commitments for responsible business conduct | E8: =[2]Nomad_Topical_Mapping!E8 -> Sustainability governance
A9: Nomad | B9: =LEFT(C9, FIND("-", C9) - 1) -> S1 | C9: =[2]Nomad_Topical_Mapping!H9 -> S1-3 | D9: =[2]Nomad_Topical_Mapping!D9 -> Mechanisms for seeking advice and raising concerns | E9: =[2]Nomad_Topical_Mapping!E9 -> Sustainability governance – Speak up programme
A10: Nomad | B10: =LEFT(C10, FIND("-", C10) - 1) -> S2 | C10: =[2]Nomad_Topical_Mapping!H10 -> S2-3 | D10: =[2]Nomad_Topical_Mapping!D10 -> Mechanisms for seeking advice and raising concerns | E10: =[2]Nomad_Topical_Mapping!E10 -> Sustainability governance – Speak up programme
A11: Nomad | B11: =LEFT(C11, FIND("-", C11) - 1) -> G1 | C11: =[2]Nomad_Topical_Mapping!H11 -> G1-1 | D11: =[2]Nomad_Topical_Mapping!D11 -> Mechanisms for seeking advice and raising concerns | E11: =[2]Nomad_Topical_Mapping!E11 -> Sustainability governance – Speak up programme
A12: Nomad | B12: =LEFT(C12, FIND("-", C12) - 1) -> G1 | C12: =[2]Nomad_Topical_Mapping!H12 -> G1-3 | D12: =[2]Nomad_Topical_Mapping!D12 -> Mechanisms for seeking advice and raising concerns | E12: =[2]Nomad_Topical_Mapping!E12 -> Sustainability governance – Speak up programme
A13: Nomad | B13: =LEFT(C13, FIND("-", C13) - 1) -> E2 | C13: =[2]Nomad_Topical_Mapping!H13 -> E2-4 | D13: =[2]Nomad_Topical_Mapping!D13 -> Commitment to legal compliance and anti-bribery outlined | E13: =[2]Nomad_Topical_Mapping!E13 -> ESG regulation and reporting / Anti-bribery and corruption
... A52: Nomad | B52: =LEFT(C52, FIND("-", C52) - 1) -> E1 | C52: =[2]Nomad_Topical_Mapping!H52 -> E1-4 | D52: =[2]Nomad_Topical_Mapping!D52 -> Reduction of GHG emissions | E52: =[2]Nomad_Topical_Mapping!E52 -> Climate change and greenhouse gases / Data tables
A53: Nomad | B53: =LEFT(C53, FIND("-", C53) - 1) -> E5 | C53: =[2]Nomad_Topical_Mapping!H54 -> E5-1 | D53: =[2]Nomad_Topical_Mapping!D54 -> Management approach — Waste | E53: =[2]Nomad_Topical_Mapping!E54 -> Waste and water / Environment Policy
A54: Nomad | B54: =LEFT(C54, FIND("-", C54) - 1) -> E5 | C54: =[2]Nomad_Topical_Mapping!H55 -> E5-2 | D54: =[2]Nomad_Topical_Mapping!D55 -> Management approach — Waste | E54: =[2]Nomad_Topical_Mapping!E55 -> Waste and water / Environment Policy
A55: Nomad | B55: =LEFT(C55, FIND("-", C55) - 1) -> E5 | C55: =[2]Nomad_Topical_Mapping!H56 -> E5-3 | D55: =[2]Nomad_Topical_Mapping!D56 -> Management approach — Waste | E55: =[2]Nomad_Topical_Mapping!E56 -> Waste and water / Environment Policy
A56: Nomad | B56: =LEFT(C56, FIND("-", C56) - 1) -> E5 | C56: =[2]Nomad_Topical_Mapping!H57 -> E5-4 | D56: =[2]Nomad_Topical_Mapping!D57 -> Operational waste profile and significant environmental impact | E56: =[2]Nomad_Topical_Mapping!E57 -> Waste and water
A57: Nomad | B57: =LEFT(C57, FIND("-", C57) - 1) -> E5 | C57: =[2]Nomad_Topical_Mapping!H58 -> E5-2 | D57: =[2]Nomad_Topical_Mapping!D58 -> Management of significant waste related impacts | E57: =[2]Nomad_Topical_Mapping!E58 -> Waste and water / Packaging
A58: Nomad | B58: =LEFT(C58, FIND("-", C58) - 1) -> E5 | C58: =[2]Nomad_Topical_Mapping!H59 -> E5-5 | D58: =[2]Nomad_Topical_Mapping!D59 -> Management of significant waste related impacts | E58: =[2]Nomad_Topical_Mapping!E59 -> Waste and water / Packaging
A59: Nomad | B59: =LEFT(C59, FIND("-", C59) - 1) -> E5 | C59: =[2]Nomad_Topical_Mapping!H60 -> E5-5 | D59: =[2]Nomad_Topical_Mapping!D60 -> Waste generated | E59: =[2]Nomad_Topical_Mapping!E60 -> Data tables
A60: Nomad | B60: =LEFT(C60, FIND("-", C60) - 1) -> E5 | C60: =[2]Nomad_Topical_Mapping!H61 -> E5-5 | D60: =[2]Nomad_Topical_Mapping!D61 -> Waste diverted from disposal | E60: =[2]Nomad_Topical_Mapping!E61 -> Waste and water / Data tables
A61: Nomad | B61: =LEFT(C61, FIND("-", C61) - 1) -> E5 | C61: =[2]Nomad_Topical_Mapping!H62 -> E5-5 | D61: =[2]Nomad_Topical_Mapping!D62 -> Waste directed to disposal | E61: =[2]Nomad_Topical_Mapping!E62 -> Waste and water / Data tables
A62: Nomad | B62: =LEFT(C62, FIND("-", C62) - 1) -> S1 | C62: =[2]Nomad_Topical_Mapping!H63 -> S1-1 | D62: =[2]Nomad_Topical_Mapping!D63 -> Management approach — OHS | E62: =[2]Nomad_Topical_Mapping!E63 -> Employee health, wellbeing and development / Data tables / Safety Policy
A63: Nomad | B63: =LEFT(C63, FIND("-", C63) - 1) -> S1 | C63: =[2]Nomad_Topical_Mapping!H64 -> S1-4 | D63: =[2]Nomad_Topical_Mapping!D64 -> Management approach — OHS | E63: =[2]Nomad_Topical_Mapping!E64 -> Employee health, wellbeing and development / Data tables / Safety Policy
A64: Nomad | B64: =LEFT(C64, FIND("-", C64) - 1) -> S1 | C64: =[2]Nomad_Topical_Mapping!H65 -> S1-5 | D64: =[2]Nomad_Topical_Mapping!D65 -> Management approach — OHS | E64: =[2]Nomad_Topical_Mapping!E65 -> Employee health, wellbeing and development / Data tables / Safety Policy
... A97: Nomad | B97: =LEFT(C97, FIND("-", C97) - 1) -> S4 | C97: =[2]Nomad_Topical_Mapping!H98 -> S4-1 | D97: =[2]Nomad_Topical_Mapping!D98 -> Management approach — Ingredient selection | E97: =[2]Nomad_Topical_Mapping!E98 -> Ingredient selection / Data tables
